Workbook

Sheet Pricing and editable planning i
A1: Pricing and editable planning inputs
A2: NaukriShield — Business Plan · Main Scenario
A4: Variable / dimension | B4: Value
A5: Student monthly free allowance | B5: =3 -> 3
A6: Cafe monthly price | B6: =499 -> 499
A7: API check price | B7: =49 -> 49
A8: Haiku cost per check | B8: =0.75 -> 0.75
A9: Cached data cost per check | B9: =1.5 -> 1.5
A10: Cost per check | B10: ='Pricing and editable planning i'!B8+'Pricing and editable planning i'!B9 -> 2.25
A11: Paying cafes | B11: =200 -> 200
A12: Year 1 API checks | B12: =30000 -> 30000
A13: Checks per cafe per month | B13: =10 -> 10
A14: Active free students | B14: =1000 -> 1000
A15: Checks per free student per month | B15: =3 -> 3
A16: Monthly non-check overhead | B16: =14692.5 -> 14692.5
A17: Opening cash assumption | B17: =300000 -> 300000

Sheet Year 1 totals and 45-cafe break
A1: Year 1 totals and 45-cafe break-even
A2: NaukriShield — Business Plan · Main Scenario
A4: Variable / dimension | B4: Value
A5: NS Year 1 revenue | B5: =SUM('Monthly revenue and check costs'!B5,'Monthly revenue and check costs'!C5,'Monthly revenue and check costs'!D5,'Monthly revenue and check costs'!E5,'Monthly revenue and check costs'!F5,'Monthly revenue and check costs'!G5,'Monthly revenue and check costs'!H5,'Monthly revenue and check costs'!I5,'Monthly revenue and check costs'!J5,'Monthly revenue and check costs'!K5,'Monthly revenue and check costs'!L5,'Monthly revenue and check costs'!M5) -> 2667600
A6: NS Year 1 check costs | B6: =SUM('Monthly revenue and check costs'!B13,'Monthly revenue and check costs'!C13,'Monthly revenue and check costs'!D13,'Monthly revenue and check costs'!E13,'Monthly revenue and check costs'!F13,'Monthly revenue and check costs'!G13,'Monthly revenue and check costs'!H13,'Monthly revenue and check costs'!I13,'Monthly revenue and check costs'!J13,'Monthly revenue and check costs'!K13,'Monthly revenue and check costs'!L13,'Monthly revenue and check costs'!M13) -> 202500
A7: NS Year 1 gross margin | B7: =IFERROR(('Year 1 totals and 45-cafe break'!B5-'Year 1 totals and 45-cafe break'!B6)/'Year 1 totals and 45-cafe break'!B5,"") -> 0.92408907
A8: NS Year 1 operating profit | B8: =SUM('Runway and operating profit'!B10,'Runway and operating profit'!C10,'Runway and operating profit'!D10,'Runway and operating profit'!E10,'Runway and operating profit'!F10,'Runway and operating profit'!G10,'Runway and operating profit'!H10,'Runway and operating profit'!I10,'Runway and operating profit'!J10,'Runway and operating profit'!K10,'Runway and operating profit'!L10,'Runway and operating profit'!M10) -> 2288790
A9: NS cafe contribution | B9: ='Pricing and editable planning i'!B6-'Pricing and editable planning i'!B13*'Pricing and editable planning i'!B10 -> 476.5
A10: NS free monthly subsidy | B10: ='Pricing and editable planning i'!B14*MIN('Pricing and editable planning i'!B15,'Pricing and editable planning i'!B5)*'Pricing and editable planning i'!B10 -> 6750
A11: NS cafe-only break-even count | B11: =IF(IF(IF(ISERROR('Year 1 totals and 45-cafe break'!B9>0),'Year 1 totals and 45-cafe break'!B9>0,IF('Year 1 totals and 45-cafe break'!B9="","",'Year 1 totals and 45-cafe break'!B9>0))="",FALSE,IF(ISERROR('Year 1 totals and 45-cafe break'!B9>0),'Year 1 totals and 45-cafe break'!B9>0,IF('Year 1 totals and 45-cafe break'!B9="","",'Year 1 totals and 45-cafe break'!B9>0))),CEILING(('Pricing and editable planning i'!B16+'Year 1 totals and 45-cafe break'!B10)/'Year 1 totals and 45-cafe break'!B9,1),"") -> 45
A12: NS break-even count with API | B12: =IF(IF(IF(ISERROR('Year 1 totals and 45-cafe break'!B9>0),'Year 1 totals and 45-cafe break'!B9>0,IF('Year 1 totals and 45-cafe break'!B9="","",'Year 1 totals and 45-cafe break'!B9>0))="",FALSE,IF(ISERROR('Year 1 totals and 45-cafe break'!B9>0),'Year 1 totals and 45-cafe break'!B9>0,IF('Year 1 totals and 45-cafe break'!B9="","",'Year 1 totals and 45-cafe break'!B9>0))),CEILING(MAX(0,'Pricing and editable planning i'!B16+'Year 1 totals and 45-cafe break'!B10-'Pricing and editable planning i'!B12/12*('Pricing and editable planning i'!B7-'Pricing and editable planning i'!B10))/'Year 1 totals and 45-cafe break'!B9,1),"") -> 0
A13: NS 45-cafe profit without API | B13: =45*'Year 1 totals and 45-cafe break'!B9-'Year 1 totals and 45-cafe break'!B10-'Pricing and editable planning i'!B16 -> 0
A14: NS cafe check-cost-only limit | B14: ='Pricing and editable planning i'!B6/'Pricing and editable planning i'!B10 -> 221.77778
A15: NS starting cash runway months | B15: =IF(IF(IF(ISERROR('Year 1 totals and 45-cafe break'!B8<0),'Year 1 totals and 45-cafe break'!B8<0,IF('Year 1 totals and 45-cafe break'!B8="","",'Year 1 totals and 45-cafe break'!B8<0))="",FALSE,IF(ISERROR('Year 1 totals and 45-cafe break'!B8<0),'Year 1 totals and 45-cafe break'!B8<0,IF('Year 1 totals and 45-cafe break'!B8="","",'Year 1 totals and 45-cafe break'!B8<0))),'Pricing and editable planning i'!B17/(-'Year 1 totals and 45-cafe break'!B8/12),"")

Sheet Monthly revenue and check costs
A1: Monthly revenue and check costs
A2: NaukriShield — Business Plan · Main Scenario
A4: Variable / dimension | B4: 2026-11 | C4: 2026-12 | D4: 2027-01 | E4: 2027-02 | F4: 2027-03 | G4: 2027-04 | H4: 2027-05 | I4: 2027-06 | J4: 2027-07 | K4: 2027-08 | L4: 2027-09 | M4: 2027-10
A5: NS revenue | B5: =SUM('Monthly revenue and check costs'!B6,'Monthly revenue and check costs'!B7,'Monthly revenue and check costs'!B8) -> 222300 | C5: =SUM('Monthly revenue and check costs'!C6,'Monthly revenue and check costs'!C7,'Monthly revenue and check costs'!C8) -> 222300 | D5: =SUM('Monthly revenue and check costs'!D6,'Monthly revenue and check costs'!D7,'Monthly revenue and check costs'!D8) -> 222300 | E5: =SUM('Monthly revenue and check costs'!E6,'Monthly revenue and check costs'!E7,'Monthly revenue and check costs'!E8) -> 222300 | F5: =SUM('Monthly revenue and check costs'!F6,'Monthly revenue and check costs'!F7,'Monthly revenue and check costs'!F8) -> 222300 | G5: =SUM('Monthly revenue and check costs'!G6,'Monthly revenue and check costs'!G7,'Monthly revenue and check costs'!G8) -> 222300 | H5: =SUM('Monthly revenue and check costs'!H6,'Monthly revenue and check costs'!H7,'Monthly revenue and check costs'!H8) -> 222300 | I5: =SUM('Monthly revenue and check costs'!I6,'Monthly revenue and check costs'!I7,'Monthly revenue and check costs'!I8) -> 222300 | ... M5: =SUM('Monthly revenue and check costs'!M6,'Monthly revenue and check costs'!M7,'Monthly revenue and check costs'!M8) -> 222300
A6: API | B6: =IF(EXACT("API","Cyber-cafes"),'Pricing and editable planning i'!B11*'Pricing and editable planning i'!B6,IF(EXACT("API","API"),'Pricing and editable planning i'!B12/12*'Pricing and editable planning i'!B7,0)) -> 122500 | C6: =IF(EXACT("API","Cyber-cafes"),'Pricing and editable planning i'!B11*'Pricing and editable planning i'!B6,IF(EXACT("API","API"),'Pricing and editable planning i'!B12/12*'Pricing and editable planning i'!B7,0)) -> 122500 | D6: =IF(EXACT("API","Cyber-cafes"),'Pricing and editable planning i'!B11*'Pricing and editable planning i'!B6,IF(EXACT("API","API"),'Pricing and editable planning i'!B12/12*'Pricing and editable planning i'!B7,0)) -> 122500 | E6: =IF(EXACT("API","Cyber-cafes"),'Pricing and editable planning i'!B11*'Pricing and editable planning i'!B6,IF(EXACT("API","API"),'Pricing and editable planning i'!B12/12*'Pricing and editable planning i'!B7,0)) -> 122500 | F6: =IF(EXACT("API","Cyber-cafes"),'Pricing and editable planning i'!B11*'Pricing and editable planning i'!B6,IF(EXACT("API","API"),'Pricing and editable planning i'!B12/12*'Pricing and editable planning i'!B7,0)) -> 122500 | G6: =IF(EXACT("API","Cyber-cafes"),'Pricing and editable planning i'!B11*'Pricing and editable planning i'!B6,IF(EXACT("API","API"),'Pricing and editable planning i'!B12/12*'Pricing and editable planning i'!B7,0)) -> 122500 | H6: =IF(EXACT("API","Cyber-cafes"),'Pricing and editable planning i'!B11*'Pricing and editable planning i'!B6,IF(EXACT("API","API"),'Pricing and editable planning i'!B12/12*'Pricing and editable planning i'!B7,0)) -> 122500 | I6: =IF(EXACT("API","Cyber-cafes"),'Pricing and editable planning i'!B11*'Pricing and editable planning i'!B6,IF(EXACT("API","API"),'Pricing and editable planning i'!B12/12*'Pricing and editable planning i'!B7,0)) -> 122500 | J6: =IF(EXACT("API","Cyber-cafes"),'Pricing and editable planning i'!B11*'Pricing and editable planning i'!B6,IF(EXACT("API","API"),'Pricing and editable planning i'!B12/12*'Pricing and editable planning i'!B7,0)) -> 122500 | K6: =IF(EXACT("API","Cyber-cafes"),'Pricing and editable planning i'!B11*'Pricing and editable planning i'!B6,IF(EXACT("API","API"),'Pricing and editable planning i'!B12/12*'Pricing and editable planning i'!B7,0)) -> 122500 | L6: =IF(EXACT("API","Cyber-cafes"),'Pricing and editable planning i'!B11*'Pricing and editable planning i'!B6,IF(EXACT("API","API"),'Pricing and editable planning i'!B12/12*'Pricing and editable planning i'!B7,0)) -> 122500 | M6: =IF(EXACT("API","Cyber-cafes"),'Pricing and editable planning i'!B11*'Pricing and editable planning i'!B6,IF(EXACT("API","API"),'Pricing and editable planning i'!B12/12*'Pricing and editable planning i'!B7,0)) -> 122500
A7: Cyber-cafes | B7: =IF(EXACT("Cyber-cafes","Cyber-cafes"),'Pricing and editable planning i'!B11*'Pricing and editable planning i'!B6,IF(EXACT("Cyber-cafes","API"),'Pricing and editable planning i'!B12/12*'Pricing and editable planning i'!B7,0)) -> 99800 | C7: =IF(EXACT("Cyber-cafes","Cyber-cafes"),'Pricing and editable planning i'!B11*'Pricing and editable planning i'!B6,IF(EXACT("Cyber-cafes","API"),'Pricing and editable planning i'!B12/12*'Pricing and editable planning i'!B7,0)) -> 99800 | D7: =IF(EXACT("Cyber-cafes","Cyber-cafes"),'Pricing and editable planning i'!B11*'Pricing and editable planning i'!B6,IF(EXACT("Cyber-cafes","API"),'Pricing and editable planning i'!B12/12*'Pricing and editable planning i'!B7,0)) -> 99800 | E7: =IF(EXACT("Cyber-cafes","Cyber-cafes"),'Pricing and editable planning i'!B11*'Pricing and editable planning i'!B6,IF(EXACT("Cyber-cafes","API"),'Pricing and editable planning i'!B12/12*'Pricing and editable planning i'!B7,0)) -> 99800 | F7: =IF(EXACT("Cyber-cafes","Cyber-cafes"),'Pricing and editable planning i'!B11*'Pricing and editable planning i'!B6,IF(EXACT("Cyber-cafes","API"),'Pricing and editable planning i'!B12/12*'Pricing and editable planning i'!B7,0)) -> 99800 | G7: =IF(EXACT("Cyber-cafes","Cyber-cafes"),'Pricing and editable planning i'!B11*'Pricing and editable planning i'!B6,IF(EXACT("Cyber-cafes","API"),'Pricing and editable planning i'!B12/12*'Pricing and editable planning i'!B7,0)) -> 99800 | H7: =IF(EXACT("Cyber-cafes","Cyber-cafes"),'Pricing and editable planning i'!B11*'Pricing and editable planning i'!B6,IF(EXACT("Cyber-cafes","API"),'Pricing and editable planning i'!B12/12*'Pricing and editable planning i'!B7,0)) -> 99800 | I7: =IF(EXACT("Cyber-cafes","Cyber-cafes"),'Pricing and editable planning i'!B11*'Pricing and editable planning i'!B6,IF(EXACT("Cyber-cafes","API"),'Pricing and editable planning i'!B12/12*'Pricing and editable planning i'!B7,0)) -> 99800 | J7: =IF(EXACT("Cyber-cafes","Cyber-cafes"),'Pricing and editable planning i'!B11*'Pricing and editable planning i'!B6,IF(EXACT("Cyber-cafes","API"),'Pricing and editable planning i'!B12/12*'Pricing and editable planning i'!B7,0)) -> 99800 | K7: =IF(EXACT("Cyber-cafes","Cyber-cafes"),'Pricing and editable planning i'!B11*'Pricing and editable planning i'!B6,IF(EXACT("Cyber-cafes","API"),'Pricing and editable planning i'!B12/12*'Pricing and editable planning i'!B7,0)) -> 99800 | L7: =IF(EXACT("Cyber-cafes","Cyber-cafes"),'Pricing and editable planning i'!B11*'Pricing and editable planning i'!B6,IF(EXACT("Cyber-cafes","API"),'Pricing and editable planning i'!B12/12*'Pricing and editable planning i'!B7,0)) -> 99800 | M7: =IF(EXACT("Cyber-cafes","Cyber-cafes"),'Pricing and editable planning i'!B11*'Pricing and editable planning i'!B6,IF(EXACT("Cyber-cafes","API"),'Pricing and editable planning i'!B12/12*'Pricing and editable planning i'!B7,0)) -> 99800
A8: Students | B8: =IF(EXACT("Students","Cyber-cafes"),'Pricing and editable planning i'!B11*'Pricing and editable planning i'!B6,IF(EXACT("Students","API"),'Pricing and editable planning i'!B12/12*'Pricing and editable planning i'!B7,0)) -> 0 | C8: =IF(EXACT("Students","Cyber-cafes"),'Pricing and editable planning i'!B11*'Pricing and editable planning i'!B6,IF(EXACT("Students","API"),'Pricing and editable planning i'!B12/12*'Pricing and editable planning i'!B7,0)) -> 0 | D8: =IF(EXACT("Students","Cyber-cafes"),'Pricing and editable planning i'!B11*'Pricing and editable planning i'!B6,IF(EXACT("Students","API"),'Pricing and editable planning i'!B12/12*'Pricing and editable planning i'!B7,0)) -> 0 | E8: =IF(EXACT("Students","Cyber-cafes"),'Pricing and editable planning i'!B11*'Pricing and editable planning i'!B6,IF(EXACT("Students","API"),'Pricing and editable planning i'!B12/12*'Pricing and editable planning i'!B7,0)) -> 0 | F8: =IF(EXACT("Students","Cyber-cafes"),'Pricing and editable planning i'!B11*'Pricing and editable planning i'!B6,IF(EXACT("Students","API"),'Pricing and editable planning i'!B12/12*'Pricing and editable planning i'!B7,0)) -> 0 | G8: =IF(EXACT("Students","Cyber-cafes"),'Pricing and editable planning i'!B11*'Pricing and editable planning i'!B6,IF(EXACT("Students","API"),'Pricing and editable planning i'!B12/12*'Pricing and editable planning i'!B7,0)) -> 0 | H8: =IF(EXACT("Students","Cyber-cafes"),'Pricing and editable planning i'!B11*'Pricing and editable planning i'!B6,IF(EXACT("Students","API"),'Pricing and editable planning i'!B12/12*'Pricing and editable planning i'!B7,0)) -> 0 | I8: =IF(EXACT("Students","Cyber-cafes"),'Pricing and editable planning i'!B11*'Pricing and editable planning i'!B6,IF(EXACT("Students","API"),'Pricing and editable planning i'!B12/12*'Pricing and editable planning i'!B7,0)) -> 0 | J8: =IF(EXACT("Students","Cyber-cafes"),'Pricing and editable planning i'!B11*'Pricing and editable planning i'!B6,IF(EXACT("Students","API"),'Pricing and editable planning i'!B12/12*'Pricing and editable planning i'!B7,0)) -> 0 | K8: =IF(EXACT("Students","Cyber-cafes"),'Pricing and editable planning i'!B11*'Pricing and editable planning i'!B6,IF(EXACT("Students","API"),'Pricing and editable planning i'!B12/12*'Pricing and editable planning i'!B7,0)) -> 0 | L8: =IF(EXACT("Students","Cyber-cafes"),'Pricing and editable planning i'!B11*'Pricing and editable planning i'!B6,IF(EXACT("Students","API"),'Pricing and editable planning i'!B12/12*'Pricing and editable planning i'!B7,0)) -> 0 | M8: =IF(EXACT("Students","Cyber-cafes"),'Pricing and editable planning i'!B11*'Pricing and editable planning i'!B6,IF(EXACT("Students","API"),'Pricing and editable planning i'!B12/12*'Pricing and editable planning i'!B7,0)) -> 0
A9: NS checks | B9: =SUM('Monthly revenue and check costs'!B10,'Monthly revenue and check costs'!B11,'Monthly revenue and check costs'!B12) -> 7500 | C9: =SUM('Monthly revenue and check costs'!C10,'Monthly revenue and check costs'!C11,'Monthly revenue and check costs'!C12) -> 7500 | D9: =SUM('Monthly revenue and check costs'!D10,'Monthly revenue and check costs'!D11,'Monthly revenue and check costs'!D12) -> 7500 | E9: =SUM('Monthly revenue and check costs'!E10,'Monthly revenue and check costs'!E11,'Monthly revenue and check costs'!E12) -> 7500 | F9: =SUM('Monthly revenue and check costs'!F10,'Monthly revenue and check costs'!F11,'Monthly revenue and check costs'!F12) -> 7500 | G9: =SUM('Monthly revenue and check costs'!G10,'Monthly revenue and check costs'!G11,'Monthly revenue and check costs'!G12) -> 7500 | H9: =SUM('Monthly revenue and check costs'!H10,'Monthly revenue and check costs'!H11,'Monthly revenue and check costs'!H12) -> 7500 | I9: =SUM('Monthly revenue and check costs'!I10,'Monthly revenue and check costs'!I11,'Monthly revenue and check costs'!I12) -> 7500 | ... M9: =SUM('Monthly revenue and check costs'!M10,'Monthly revenue and check costs'!M11,'Monthly revenue and check costs'!M12) -> 7500
A10: API | B10: =IF(EXACT("API","Cyber-cafes"),'Pricing and editable planning i'!B11*'Pricing and editable planning i'!B13,IF(EXACT("API","API"),'Pricing and editable planning i'!B12/12,'Pricing and editable planning i'!B14*MIN('Pricing and editable planning i'!B15,'Pricing and editable planning i'!B5))) -> 2500 | C10: =IF(EXACT("API","Cyber-cafes"),'Pricing and editable planning i'!B11*'Pricing and editable planning i'!B13,IF(EXACT("API","API"),'Pricing and editable planning i'!B12/12,'Pricing and editable planning i'!B14*MIN('Pricing and editable planning i'!B15,'Pricing and editable planning i'!B5))) -> 2500 | D10: =IF(EXACT("API","Cyber-cafes"),'Pricing and editable planning i'!B11*'Pricing and editable planning i'!B13,IF(EXACT("API","API"),'Pricing and editable planning i'!B12/12,'Pricing and editable planning i'!B14*MIN('Pricing and editable planning i'!B15,'Pricing and editable planning i'!B5))) -> 2500 | E10: =IF(EXACT("API","Cyber-cafes"),'Pricing and editable planning i'!B11*'Pricing and editable planning i'!B13,IF(EXACT("API","API"),'Pricing and editable planning i'!B12/12,'Pricing and editable planning i'!B14*MIN('Pricing and editable planning i'!B15,'Pricing and editable planning i'!B5))) -> 2500 | F10: =IF(EXACT("API","Cyber-cafes"),'Pricing and editable planning i'!B11*'Pricing and editable planning i'!B13,IF(EXACT("API","API"),'Pricing and editable planning i'!B12/12,'Pricing and editable planning i'!B14*MIN('Pricing and editable planning i'!B15,'Pricing and editable planning i'!B5))) -> 2500 | G10: =IF(EXACT("API","Cyber-cafes"),'Pricing and editable planning i'!B11*'Pricing and editable planning i'!B13,IF(EXACT("API","API"),'Pricing and editable planning i'!B12/12,'Pricing and editable planning i'!B14*MIN('Pricing and editable planning i'!B15,'Pricing and editable planning i'!B5))) -> 2500 | H10: =IF(EXACT("API","Cyber-cafes"),'Pricing and editable planning i'!B11*'Pricing and editable planning i'!B13,IF(EXACT("API","API"),'Pricing and editable planning i'!B12/12,'Pricing and editable planning i'!B14*MIN('Pricing and editable planning i'!B15,'Pricing and editable planning i'!B5))) -> 2500 | I10: =IF(EXACT("API","Cyber-cafes"),'Pricing and editable planning i'!B11*'Pricing and editable planning i'!B13,IF(EXACT("API","API"),'Pricing and editable planning i'!B12/12,'Pricing and editable planning i'!B14*MIN('Pricing and editable planning i'!B15,'Pricing and editable planning i'!B5))) -> 2500 | J10: =IF(EXACT("API","Cyber-cafes"),'Pricing and editable planning i'!B11*'Pricing and editable planning i'!B13,IF(EXACT("API","API"),'Pricing and editable planning i'!B12/12,'Pricing and editable planning i'!B14*MIN('Pricing and editable planning i'!B15,'Pricing and editable planning i'!B5))) -> 2500 | K10: =IF(EXACT("API","Cyber-cafes"),'Pricing and editable planning i'!B11*'Pricing and editable planning i'!B13,IF(EXACT("API","API"),'Pricing and editable planning i'!B12/12,'Pricing and editable planning i'!B14*MIN('Pricing and editable planning i'!B15,'Pricing and editable planning i'!B5))) -> 2500 | L10: =IF(EXACT("API","Cyber-cafes"),'Pricing and editable planning i'!B11*'Pricing and editable planning i'!B13,IF(EXACT("API","API"),'Pricing and editable planning i'!B12/12,'Pricing and editable planning i'!B14*MIN('Pricing and editable planning i'!B15,'Pricing and editable planning i'!B5))) -> 2500 | M10: =IF(EXACT("API","Cyber-cafes"),'Pricing and editable planning i'!B11*'Pricing and editable planning i'!B13,IF(EXACT("API","API"),'Pricing and editable planning i'!B12/12,'Pricing and editable planning i'!B14*MIN('Pricing and editable planning i'!B15,'Pricing and editable planning i'!B5))) -> 2500
A11: Cyber-cafes | B11: =IF(EXACT("Cyber-cafes","Cyber-cafes"),'Pricing and editable planning i'!B11*'Pricing and editable planning i'!B13,IF(EXACT("Cyber-cafes","API"),'Pricing and editable planning i'!B12/12,'Pricing and editable planning i'!B14*MIN('Pricing and editable planning i'!B15,'Pricing and editable planning i'!B5))) -> 2000 | C11: =IF(EXACT("Cyber-cafes","Cyber-cafes"),'Pricing and editable planning i'!B11*'Pricing and editable planning i'!B13,IF(EXACT("Cyber-cafes","API"),'Pricing and editable planning i'!B12/12,'Pricing and editable planning i'!B14*MIN('Pricing and editable planning i'!B15,'Pricing and editable planning i'!B5))) -> 2000 | D11: =IF(EXACT("Cyber-cafes","Cyber-cafes"),'Pricing and editable planning i'!B11*'Pricing and editable planning i'!B13,IF(EXACT("Cyber-cafes","API"),'Pricing and editable planning i'!B12/12,'Pricing and editable planning i'!B14*MIN('Pricing and editable planning i'!B15,'Pricing and editable planning i'!B5))) -> 2000 | E11: =IF(EXACT("Cyber-cafes","Cyber-cafes"),'Pricing and editable planning i'!B11*'Pricing and editable planning i'!B13,IF(EXACT("Cyber-cafes","API"),'Pricing and editable planning i'!B12/12,'Pricing and editable planning i'!B14*MIN('Pricing and editable planning i'!B15,'Pricing and editable planning i'!B5))) -> 2000 | F11: =IF(EXACT("Cyber-cafes","Cyber-cafes"),'Pricing and editable planning i'!B11*'Pricing and editable planning i'!B13,IF(EXACT("Cyber-cafes","API"),'Pricing and editable planning i'!B12/12,'Pricing and editable planning i'!B14*MIN('Pricing and editable planning i'!B15,'Pricing and editable planning i'!B5))) -> 2000 | G11: =IF(EXACT("Cyber-cafes","Cyber-cafes"),'Pricing and editable planning i'!B11*'Pricing and editable planning i'!B13,IF(EXACT("Cyber-cafes","API"),'Pricing and editable planning i'!B12/12,'Pricing and editable planning i'!B14*MIN('Pricing and editable planning i'!B15,'Pricing and editable planning i'!B5))) -> 2000 | H11: =IF(EXACT("Cyber-cafes","Cyber-cafes"),'Pricing and editable planning i'!B11*'Pricing and editable planning i'!B13,IF(EXACT("Cyber-cafes","API"),'Pricing and editable planning i'!B12/12,'Pricing and editable planning i'!B14*MIN('Pricing and editable planning i'!B15,'Pricing and editable planning i'!B5))) -> 2000 | I11: =IF(EXACT("Cyber-cafes","Cyber-cafes"),'Pricing and editable planning i'!B11*'Pricing and editable planning i'!B13,IF(EXACT("Cyber-cafes","API"),'Pricing and editable planning i'!B12/12,'Pricing and editable planning i'!B14*MIN('Pricing and editable planning i'!B15,'Pricing and editable planning i'!B5))) -> 2000 | J11: =IF(EXACT("Cyber-cafes","Cyber-cafes"),'Pricing and editable planning i'!B11*'Pricing and editable planning i'!B13,IF(EXACT("Cyber-cafes","API"),'Pricing and editable planning i'!B12/12,'Pricing and editable planning i'!B14*MIN('Pricing and editable planning i'!B15,'Pricing and editable planning i'!B5))) -> 2000 | K11: =IF(EXACT("Cyber-cafes","Cyber-cafes"),'Pricing and editable planning i'!B11*'Pricing and editable planning i'!B13,IF(EXACT("Cyber-cafes","API"),'Pricing and editable planning i'!B12/12,'Pricing and editable planning i'!B14*MIN('Pricing and editable planning i'!B15,'Pricing and editable planning i'!B5))) -> 2000 | L11: =IF(EXACT("Cyber-cafes","Cyber-cafes"),'Pricing and editable planning i'!B11*'Pricing and editable planning i'!B13,IF(EXACT("Cyber-cafes","API"),'Pricing and editable planning i'!B12/12,'Pricing and editable planning i'!B14*MIN('Pricing and editable planning i'!B15,'Pricing and editable planning i'!B5))) -> 2000 | M11: =IF(EXACT("Cyber-cafes","Cyber-cafes"),'Pricing and editable planning i'!B11*'Pricing and editable planning i'!B13,IF(EXACT("Cyber-cafes","API"),'Pricing and editable planning i'!B12/12,'Pricing and editable planning i'!B14*MIN('Pricing and editable planning i'!B15,'Pricing and editable planning i'!B5))) -> 2000
A12: Students | B12: =IF(EXACT("Students","Cyber-cafes"),'Pricing and editable planning i'!B11*'Pricing and editable planning i'!B13,IF(EXACT("Students","API"),'Pricing and editable planning i'!B12/12,'Pricing and editable planning i'!B14*MIN('Pricing and editable planning i'!B15,'Pricing and editable planning i'!B5))) -> 3000 | C12: =IF(EXACT("Students","Cyber-cafes"),'Pricing and editable planning i'!B11*'Pricing and editable planning i'!B13,IF(EXACT("Students","API"),'Pricing and editable planning i'!B12/12,'Pricing and editable planning i'!B14*MIN('Pricing and editable planning i'!B15,'Pricing and editable planning i'!B5))) -> 3000 | D12: =IF(EXACT("Students","Cyber-cafes"),'Pricing and editable planning i'!B11*'Pricing and editable planning i'!B13,IF(EXACT("Students","API"),'Pricing and editable planning i'!B12/12,'Pricing and editable planning i'!B14*MIN('Pricing and editable planning i'!B15,'Pricing and editable planning i'!B5))) -> 3000 | E12: =IF(EXACT("Students","Cyber-cafes"),'Pricing and editable planning i'!B11*'Pricing and editable planning i'!B13,IF(EXACT("Students","API"),'Pricing and editable planning i'!B12/12,'Pricing and editable planning i'!B14*MIN('Pricing and editable planning i'!B15,'Pricing and editable planning i'!B5))) -> 3000 | F12: =IF(EXACT("Students","Cyber-cafes"),'Pricing and editable planning i'!B11*'Pricing and editable planning i'!B13,IF(EXACT("Students","API"),'Pricing and editable planning i'!B12/12,'Pricing and editable planning i'!B14*MIN('Pricing and editable planning i'!B15,'Pricing and editable planning i'!B5))) -> 3000 | G12: =IF(EXACT("Students","Cyber-cafes"),'Pricing and editable planning i'!B11*'Pricing and editable planning i'!B13,IF(EXACT("Students","API"),'Pricing and editable planning i'!B12/12,'Pricing and editable planning i'!B14*MIN('Pricing and editable planning i'!B15,'Pricing and editable planning i'!B5))) -> 3000 | H12: =IF(EXACT("Students","Cyber-cafes"),'Pricing and editable planning i'!B11*'Pricing and editable planning i'!B13,IF(EXACT("Students","API"),'Pricing and editable planning i'!B12/12,'Pricing and editable planning i'!B14*MIN('Pricing and editable planning i'!B15,'Pricing and editable planning i'!B5))) -> 3000 | I12: =IF(EXACT("Students","Cyber-cafes"),'Pricing and editable planning i'!B11*'Pricing and editable planning i'!B13,IF(EXACT("Students","API"),'Pricing and editable planning i'!B12/12,'Pricing and editable planning i'!B14*MIN('Pricing and editable planning i'!B15,'Pricing and editable planning i'!B5))) -> 3000 | J12: =IF(EXACT("Students","Cyber-cafes"),'Pricing and editable planning i'!B11*'Pricing and editable planning i'!B13,IF(EXACT("Students","API"),'Pricing and editable planning i'!B12/12,'Pricing and editable planning i'!B14*MIN('Pricing and editable planning i'!B15,'Pricing and editable planning i'!B5))) -> 3000 | K12: =IF(EXACT("Students","Cyber-cafes"),'Pricing and editable planning i'!B11*'Pricing and editable planning i'!B13,IF(EXACT("Students","API"),'Pricing and editable planning i'!B12/12,'Pricing and editable planning i'!B14*MIN('Pricing and editable planning i'!B15,'Pricing and editable planning i'!B5))) -> 3000 | L12: =IF(EXACT("Students","Cyber-cafes"),'Pricing and editable planning i'!B11*'Pricing and editable planning i'!B13,IF(EXACT("Students","API"),'Pricing and editable planning i'!B12/12,'Pricing and editable planning i'!B14*MIN('Pricing and editable planning i'!B15,'Pricing and editable planning i'!B5))) -> 3000 | M12: =IF(EXACT("Students","Cyber-cafes"),'Pricing and editable planning i'!B11*'Pricing and editable planning i'!B13,IF(EXACT("Students","API"),'Pricing and editable planning i'!B12/12,'Pricing and editable planning i'!B14*MIN('Pricing and editable planning i'!B15,'Pricing and editable planning i'!B5))) -> 3000
A13: NS check costs | B13: =SUM('Monthly revenue and check costs'!B14,'Monthly revenue and check costs'!B15,'Monthly revenue and check costs'!B16) -> 16875 | C13: =SUM('Monthly revenue and check costs'!C14,'Monthly revenue and check costs'!C15,'Monthly revenue and check costs'!C16) -> 16875 | D13: =SUM('Monthly revenue and check costs'!D14,'Monthly revenue and check costs'!D15,'Monthly revenue and check costs'!D16) -> 16875 | E13: =SUM('Monthly revenue and check costs'!E14,'Monthly revenue and check costs'!E15,'Monthly revenue and check costs'!E16) -> 16875 | F13: =SUM('Monthly revenue and check costs'!F14,'Monthly revenue and check costs'!F15,'Monthly revenue and check costs'!F16) -> 16875 | G13: =SUM('Monthly revenue and check costs'!G14,'Monthly revenue and check costs'!G15,'Monthly revenue and check costs'!G16) -> 16875 | H13: =SUM('Monthly revenue and check costs'!H14,'Monthly revenue and check costs'!H15,'Monthly revenue and check costs'!H16) -> 16875 | I13: =SUM('Monthly revenue and check costs'!I14,'Monthly revenue and check costs'!I15,'Monthly revenue and check costs'!I16) -> 16875 | ... M13: =SUM('Monthly revenue and check costs'!M14,'Monthly revenue and check costs'!M15,'Monthly revenue and check costs'!M16) -> 16875
A14: API | B14: ='Monthly revenue and check costs'!B10*'Pricing and editable planning i'!B10 -> 5625 | C14: ='Monthly revenue and check costs'!C10*'Pricing and editable planning i'!B10 -> 5625 | D14: ='Monthly revenue and check costs'!D10*'Pricing and editable planning i'!B10 -> 5625 | E14: ='Monthly revenue and check costs'!E10*'Pricing and editable planning i'!B10 -> 5625 | F14: ='Monthly revenue and check costs'!F10*'Pricing and editable planning i'!B10 -> 5625 | G14: ='Monthly revenue and check costs'!G10*'Pricing and editable planning i'!B10 -> 5625 | H14: ='Monthly revenue and check costs'!H10*'Pricing and editable planning i'!B10 -> 5625 | I14: ='Monthly revenue and check costs'!I10*'Pricing and editable planning i'!B10 -> 5625 | J14: ='Monthly revenue and check costs'!J10*'Pricing and editable planning i'!B10 -> 5625 | K14: ='Monthly revenue and check costs'!K10*'Pricing and editable planning i'!B10 -> 5625 | L14: ='Monthly revenue and check costs'!L10*'Pricing and editable planning i'!B10 -> 5625 | M14: ='Monthly revenue and check costs'!M10*'Pricing and editable planning i'!B10 -> 5625
A15: Cyber-cafes | B15: ='Monthly revenue and check costs'!B11*'Pricing and editable planning i'!B10 -> 4500 | C15: ='Monthly revenue and check costs'!C11*'Pricing and editable planning i'!B10 -> 4500 | D15: ='Monthly revenue and check costs'!D11*'Pricing and editable planning i'!B10 -> 4500 | E15: ='Monthly revenue and check costs'!E11*'Pricing and editable planning i'!B10 -> 4500 | F15: ='Monthly revenue and check costs'!F11*'Pricing and editable planning i'!B10 -> 4500 | G15: ='Monthly revenue and check costs'!G11*'Pricing and editable planning i'!B10 -> 4500 | H15: ='Monthly revenue and check costs'!H11*'Pricing and editable planning i'!B10 -> 4500 | I15: ='Monthly revenue and check costs'!I11*'Pricing and editable planning i'!B10 -> 4500 | J15: ='Monthly revenue and check costs'!J11*'Pricing and editable planning i'!B10 -> 4500 | K15: ='Monthly revenue and check costs'!K11*'Pricing and editable planning i'!B10 -> 4500 | L15: ='Monthly revenue and check costs'!L11*'Pricing and editable planning i'!B10 -> 4500 | M15: ='Monthly revenue and check costs'!M11*'Pricing and editable planning i'!B10 -> 4500
A16: Students | B16: ='Monthly revenue and check costs'!B12*'Pricing and editable planning i'!B10 -> 6750 | C16: ='Monthly revenue and check costs'!C12*'Pricing and editable planning i'!B10 -> 6750 | D16: ='Monthly revenue and check costs'!D12*'Pricing and editable planning i'!B10 -> 6750 | E16: ='Monthly revenue and check costs'!E12*'Pricing and editable planning i'!B10 -> 6750 | F16: ='Monthly revenue and check costs'!F12*'Pricing and editable planning i'!B10 -> 6750 | G16: ='Monthly revenue and check costs'!G12*'Pricing and editable planning i'!B10 -> 6750 | H16: ='Monthly revenue and check costs'!H12*'Pricing and editable planning i'!B10 -> 6750 | I16: ='Monthly revenue and check costs'!I12*'Pricing and editable planning i'!B10 -> 6750 | J16: ='Monthly revenue and check costs'!J12*'Pricing and editable planning i'!B10 -> 6750 | K16: ='Monthly revenue and check costs'!K12*'Pricing and editable planning i'!B10 -> 6750 | L16: ='Monthly revenue and check costs'!L12*'Pricing and editable planning i'!B10 -> 6750 | M16: ='Monthly revenue and check costs'!M12*'Pricing and editable planning i'!B10 -> 6750

Sheet Runway and operating profit
A1: Runway and operating profit
A2: NaukriShield — Business Plan · Main Scenario
A4: Variable / dimension | B4: 2026-11 | C4: 2026-12 | D4: 2027-01 | E4: 2027-02 | F4: 2027-03 | G4: 2027-04 | H4: 2027-05 | I4: 2027-06 | J4: 2027-07 | K4: 2027-08 | L4: 2027-09 | M4: 2027-10
A5: NS revenue | B5: =SUM('Monthly revenue and check costs'!B6,'Monthly revenue and check costs'!B7,'Monthly revenue and check costs'!B8) -> 222300 | C5: =SUM('Monthly revenue and check costs'!C6,'Monthly revenue and check costs'!C7,'Monthly revenue and check costs'!C8) -> 222300 | D5: =SUM('Monthly revenue and check costs'!D6,'Monthly revenue and check costs'!D7,'Monthly revenue and check costs'!D8) -> 222300 | E5: =SUM('Monthly revenue and check costs'!E6,'Monthly revenue and check costs'!E7,'Monthly revenue and check costs'!E8) -> 222300 | F5: =SUM('Monthly revenue and check costs'!F6,'Monthly revenue and check costs'!F7,'Monthly revenue and check costs'!F8) -> 222300 | G5: =SUM('Monthly revenue and check costs'!G6,'Monthly revenue and check costs'!G7,'Monthly revenue and check costs'!G8) -> 222300 | H5: =SUM('Monthly revenue and check costs'!H6,'Monthly revenue and check costs'!H7,'Monthly revenue and check costs'!H8) -> 222300 | I5: =SUM('Monthly revenue and check costs'!I6,'Monthly revenue and check costs'!I7,'Monthly revenue and check costs'!I8) -> 222300 | ... M5: =SUM('Monthly revenue and check costs'!M6,'Monthly revenue and check costs'!M7,'Monthly revenue and check costs'!M8) -> 222300
A6: NS check costs | B6: =SUM('Monthly revenue and check costs'!B14,'Monthly revenue and check costs'!B15,'Monthly revenue and check costs'!B16) -> 16875 | C6: =SUM('Monthly revenue and check costs'!C14,'Monthly revenue and check costs'!C15,'Monthly revenue and check costs'!C16) -> 16875 | D6: =SUM('Monthly revenue and check costs'!D14,'Monthly revenue and check costs'!D15,'Monthly revenue and check costs'!D16) -> 16875 | E6: =SUM('Monthly revenue and check costs'!E14,'Monthly revenue and check costs'!E15,'Monthly revenue and check costs'!E16) -> 16875 | F6: =SUM('Monthly revenue and check costs'!F14,'Monthly revenue and check costs'!F15,'Monthly revenue and check costs'!F16) -> 16875 | G6: =SUM('Monthly revenue and check costs'!G14,'Monthly revenue and check costs'!G15,'Monthly revenue and check costs'!G16) -> 16875 | H6: =SUM('Monthly revenue and check costs'!H14,'Monthly revenue and check costs'!H15,'Monthly revenue and check costs'!H16) -> 16875 | I6: =SUM('Monthly revenue and check costs'!I14,'Monthly revenue and check costs'!I15,'Monthly revenue and check costs'!I16) -> 16875 | ... M6: =SUM('Monthly revenue and check costs'!M14,'Monthly revenue and check costs'!M15,'Monthly revenue and check costs'!M16) -> 16875
A7: NS gross profit | B7: ='Runway and operating profit'!B5-'Runway and operating profit'!B6 -> 205425 | C7: ='Runway and operating profit'!C5-'Runway and operating profit'!C6 -> 205425 | D7: ='Runway and operating profit'!D5-'Runway and operating profit'!D6 -> 205425 | E7: ='Runway and operating profit'!E5-'Runway and operating profit'!E6 -> 205425 | F7: ='Runway and operating profit'!F5-'Runway and operating profit'!F6 -> 205425 | G7: ='Runway and operating profit'!G5-'Runway and operating profit'!G6 -> 205425 | H7: ='Runway and operating profit'!H5-'Runway and operating profit'!H6 -> 205425 | I7: ='Runway and operating profit'!I5-'Runway and operating profit'!I6 -> 205425 | ... M7: ='Runway and operating profit'!M5-'Runway and operating profit'!M6 -> 205425
A8: NS gross margin | B8: =IFERROR('Runway and operating profit'!B7/'Runway and operating profit'!B5,"") -> 0.92408907 | C8: =IFERROR('Runway and operating profit'!C7/'Runway and operating profit'!C5,"") -> 0.92408907 | D8: =IFERROR('Runway and operating profit'!D7/'Runway and operating profit'!D5,"") -> 0.92408907 | E8: =IFERROR('Runway and operating profit'!E7/'Runway and operating profit'!E5,"") -> 0.92408907 | F8: =IFERROR('Runway and operating profit'!F7/'Runway and operating profit'!F5,"") -> 0.92408907 | G8: =IFERROR('Runway and operating profit'!G7/'Runway and operating profit'!G5,"") -> 0.92408907 | H8: =IFERROR('Runway and operating profit'!H7/'Runway and operating profit'!H5,"") -> 0.92408907 | I8: =IFERROR('Runway and operating profit'!I7/'Runway and operating profit'!I5,"") -> 0.92408907 | ... M8: =IFERROR('Runway and operating profit'!M7/'Runway and operating profit'!M5,"") -> 0.92408907
A9: NS overhead | B9: =IF('Pricing and editable planning i'!B16="","",'Pricing and editable planning i'!B16) -> 14692.5 | C9: =IF('Pricing and editable planning i'!B16="","",'Pricing and editable planning i'!B16) -> 14692.5 | D9: =IF('Pricing and editable planning i'!B16="","",'Pricing and editable planning i'!B16) -> 14692.5 | E9: =IF('Pricing and editable planning i'!B16="","",'Pricing and editable planning i'!B16) -> 14692.5 | F9: =IF('Pricing and editable planning i'!B16="","",'Pricing and editable planning i'!B16) -> 14692.5 | G9: =IF('Pricing and editable planning i'!B16="","",'Pricing and editable planning i'!B16) -> 14692.5 | H9: =IF('Pricing and editable planning i'!B16="","",'Pricing and editable planning i'!B16) -> 14692.5 | I9: =IF('Pricing and editable planning i'!B16="","",'Pricing and editable planning i'!B16) -> 14692.5 | J9: =IF('Pricing and editable planning i'!B16="","",'Pricing and editable planning i'!B16) -> 14692.5 | K9: =IF('Pricing and editable planning i'!B16="","",'Pricing and editable planning i'!B16) -> 14692.5 | L9: =IF('Pricing and editable planning i'!B16="","",'Pricing and editable planning i'!B16) -> 14692.5 | M9: =IF('Pricing and editable planning i'!B16="","",'Pricing and editable planning i'!B16) -> 14692.5
A10: NS operating profit | B10: ='Runway and operating profit'!B7-'Runway and operating profit'!B9 -> 190732.5 | C10: ='Runway and operating profit'!C7-'Runway and operating profit'!C9 -> 190732.5 | D10: ='Runway and operating profit'!D7-'Runway and operating profit'!D9 -> 190732.5 | E10: ='Runway and operating profit'!E7-'Runway and operating profit'!E9 -> 190732.5 | F10: ='Runway and operating profit'!F7-'Runway and operating profit'!F9 -> 190732.5 | G10: ='Runway and operating profit'!G7-'Runway and operating profit'!G9 -> 190732.5 | H10: ='Runway and operating profit'!H7-'Runway and operating profit'!H9 -> 190732.5 | I10: ='Runway and operating profit'!I7-'Runway and operating profit'!I9 -> 190732.5 | ... M10: ='Runway and operating profit'!M7-'Runway and operating profit'!M9 -> 190732.5
A11: NS opening cash | B11: =IF('Pricing and editable planning i'!B17="","",'Pricing and editable planning i'!B17) -> 300000 | C11: =IF('Runway and operating profit'!B12="","",'Runway and operating profit'!B12) -> 490732.5 | D11: =IF('Runway and operating profit'!C12="","",'Runway and operating profit'!C12) -> 681465 | E11: =IF('Runway and operating profit'!D12="","",'Runway and operating profit'!D12) -> 872197.5 | F11: =IF('Runway and operating profit'!E12="","",'Runway and operating profit'!E12) -> 1062930 | G11: =IF('Runway and operating profit'!F12="","",'Runway and operating profit'!F12) -> 1253662.5 | H11: =IF('Runway and operating profit'!G12="","",'Runway and operating profit'!G12) -> 1444395 | I11: =IF('Runway and operating profit'!H12="","",'Runway and operating profit'!H12) -> 1635127.5 | J11: =IF('Runway and operating profit'!I12="","",'Runway and operating profit'!I12) -> 1825860 | ... M11: =IF('Runway and operating profit'!L12="","",'Runway and operating profit'!L12) -> 2398057.5
A12: NS closing cash | B12: ='Runway and operating profit'!B11+'Runway and operating profit'!B10 -> 490732.5 | C12: ='Runway and operating profit'!C11+'Runway and operating profit'!C10 -> 681465 | D12: ='Runway and operating profit'!D11+'Runway and operating profit'!D10 -> 872197.5 | E12: ='Runway and operating profit'!E11+'Runway and operating profit'!E10 -> 1062930 | F12: ='Runway and operating profit'!F11+'Runway and operating profit'!F10 -> 1253662.5 | G12: ='Runway and operating profit'!G11+'Runway and operating profit'!G10 -> 1444395 | H12: ='Runway and operating profit'!H11+'Runway and operating profit'!H10 -> 1635127.5 | I12: ='Runway and operating profit'!I11+'Runway and operating profit'!I10 -> 1825860 | ... M12: ='Runway and operating profit'!M11+'Runway and operating profit'!M10 -> 2588790
A13: NS monthly burn | B13: =MAX(0,-'Runway and operating profit'!B10) -> 0 | C13: =MAX(0,-'Runway and operating profit'!C10) -> 0 | D13: =MAX(0,-'Runway and operating profit'!D10) -> 0 | E13: =MAX(0,-'Runway and operating profit'!E10) -> 0 | F13: =MAX(0,-'Runway and operating profit'!F10) -> 0 | G13: =MAX(0,-'Runway and operating profit'!G10) -> 0 | H13: =MAX(0,-'Runway and operating profit'!H10) -> 0 | I13: =MAX(0,-'Runway and operating profit'!I10) -> 0 | ... M13: =MAX(0,-'Runway and operating profit'!M10) -> 0
A14: NS cash runway months | B14: =IF(IF(IF(ISERROR('Runway and operating profit'!B13>0),'Runway and operating profit'!B13>0,IF('Runway and operating profit'!B13="","",'Runway and operating profit'!B13>0))="",FALSE,IF(ISERROR('Runway and operating profit'!B13>0),'Runway and operating profit'!B13>0,IF('Runway and operating profit'!B13="","",'Runway and operating profit'!B13>0))),'Runway and operating profit'!B12/'Runway and operating profit'!B13,"") | C14: =IF(IF(IF(ISERROR('Runway and operating profit'!C13>0),'Runway and operating profit'!C13>0,IF('Runway and operating profit'!C13="","",'Runway and operating profit'!C13>0))="",FALSE,IF(ISERROR('Runway and operating profit'!C13>0),'Runway and operating profit'!C13>0,IF('Runway and operating profit'!C13="","",'Runway and operating profit'!C13>0))),'Runway and operating profit'!C12/'Runway and operating profit'!C13,"") | D14: =IF(IF(IF(ISERROR('Runway and operating profit'!D13>0),'Runway and operating profit'!D13>0,IF('Runway and operating profit'!D13="","",'Runway and operating profit'!D13>0))="",FALSE,IF(ISERROR('Runway and operating profit'!D13>0),'Runway and operating profit'!D13>0,IF('Runway and operating profit'!D13="","",'Runway and operating profit'!D13>0))),'Runway and operating profit'!D12/'Runway and operating profit'!D13,"") | E14: =IF(IF(IF(ISERROR('Runway and operating profit'!E13>0),'Runway and operating profit'!E13>0,IF('Runway and operating profit'!E13="","",'Runway and operating profit'!E13>0))="",FALSE,IF(ISERROR('Runway and operating profit'!E13>0),'Runway and operating profit'!E13>0,IF('Runway and operating profit'!E13="","",'Runway and operating profit'!E13>0))),'Runway and operating profit'!E12/'Runway and operating profit'!E13,"") | F14: =IF(IF(IF(ISERROR('Runway and operating profit'!F13>0),'Runway and operating profit'!F13>0,IF('Runway and operating profit'!F13="","",'Runway and operating profit'!F13>0))="",FALSE,IF(ISERROR('Runway and operating profit'!F13>0),'Runway and operating profit'!F13>0,IF('Runway and operating profit'!F13="","",'Runway and operating profit'!F13>0))),'Runway and operating profit'!F12/'Runway and operating profit'!F13,"") | G14: =IF(IF(IF(ISERROR('Runway and operating profit'!G13>0),'Runway and operating profit'!G13>0,IF('Runway and operating profit'!G13="","",'Runway and operating profit'!G13>0))="",FALSE,IF(ISERROR('Runway and operating profit'!G13>0),'Runway and operating profit'!G13>0,IF('Runway and operating profit'!G13="","",'Runway and operating profit'!G13>0))),'Runway and operating profit'!G12/'Runway and operating profit'!G13,"") | H14: =IF(IF(IF(ISERROR('Runway and operating profit'!H13>0),'Runway and operating profit'!H13>0,IF('Runway and operating profit'!H13="","",'Runway and operating profit'!H13>0))="",FALSE,IF(ISERROR('Runway and operating profit'!H13>0),'Runway and operating profit'!H13>0,IF('Runway and operating profit'!H13="","",'Runway and operating profit'!H13>0))),'Runway and operating profit'!H12/'Runway and operating profit'!H13,"") | I14: =IF(IF(IF(ISERROR('Runway and operating profit'!I13>0),'Runway and operating profit'!I13>0,IF('Runway and operating profit'!I13="","",'Runway and operating profit'!I13>0))="",FALSE,IF(ISERROR('Runway and operating profit'!I13>0),'Runway and operating profit'!I13>0,IF('Runway and operating profit'!I13="","",'Runway and operating profit'!I13>0))),'Runway and operating profit'!I12/'Runway and operating profit'!I13,"") | ... M14: =IF(IF(IF(ISERROR('Runway and operating profit'!M13>0),'Runway and operating profit'!M13>0,IF('Runway and operating profit'!M13="","",'Runway and operating profit'!M13>0))="",FALSE,IF(ISERROR('Runway and operating profit'!M13>0),'Runway and operating profit'!M13>0,IF('Runway and operating profit'!M13="","",'Runway and operating profit'!M13>0))),'Runway and operating profit'!M12/'Runway and operating profit'!M13,"")

Sheet Year 1 scenario comparison
A1: Year 1 scenario comparison
A2: NaukriShield — Business Plan · Main Scenario
A4: Variable / dimension | B4: Value | C4: Value > NaukriShield — Downside | D4: Value > NaukriShield — Upside
A5: NS Year 1 revenue | B5: =SUM('Monthly revenue and check costs'!B5,'Monthly revenue and check costs'!C5,'Monthly revenue and check costs'!D5,'Monthly revenue and check costs'!E5,'Monthly revenue and check costs'!F5,'Monthly revenue and check costs'!G5,'Monthly revenue and check costs'!H5,'Monthly revenue and check costs'!I5,'Monthly revenue and check costs'!J5,'Monthly revenue and check costs'!K5,'Monthly revenue and check costs'!L5,'Monthly revenue and check costs'!M5) -> 2667600 | C5: =SUM('Model inputs'!N38,'Model inputs'!O38,'Model inputs'!P38,'Model inputs'!Q38,'Model inputs'!R38,'Model inputs'!S38,'Model inputs'!T38,'Model inputs'!U38,'Model inputs'!V38,'Model inputs'!W38,'Model inputs'!X38,'Model inputs'!Y38) -> 119760 | D5: =SUM('Model inputs'!N37,'Model inputs'!O37,'Model inputs'!P37,'Model inputs'!Q37,'Model inputs'!R37,'Model inputs'!S37,'Model inputs'!T37,'Model inputs'!U37,'Model inputs'!V37,'Model inputs'!W37,'Model inputs'!X37,'Model inputs'!Y37) -> 4736400
A6: NS Year 1 check costs | B6: =SUM('Monthly revenue and check costs'!B13,'Monthly revenue and check costs'!C13,'Monthly revenue and check costs'!D13,'Monthly revenue and check costs'!E13,'Monthly revenue and check costs'!F13,'Monthly revenue and check costs'!G13,'Monthly revenue and check costs'!H13,'Monthly revenue and check costs'!I13,'Monthly revenue and check costs'!J13,'Monthly revenue and check costs'!K13,'Monthly revenue and check costs'!L13,'Monthly revenue and check costs'!M13) -> 202500 | C6: =SUM('Model inputs'!N26,'Model inputs'!O26,'Model inputs'!P26,'Model inputs'!Q26,'Model inputs'!R26,'Model inputs'!S26,'Model inputs'!T26,'Model inputs'!U26,'Model inputs'!V26,'Model inputs'!W26,'Model inputs'!X26,'Model inputs'!Y26) -> 86400 | D6: =SUM('Model inputs'!N25,'Model inputs'!O25,'Model inputs'!P25,'Model inputs'!Q25,'Model inputs'!R25,'Model inputs'!S25,'Model inputs'!T25,'Model inputs'!U25,'Model inputs'!V25,'Model inputs'!W25,'Model inputs'!X25,'Model inputs'!Y25) -> 459000
A7: NS Year 1 gross margin | B7: =IFERROR(('Year 1 scenario comparison'!B5-'Year 1 scenario comparison'!B6)/'Year 1 scenario comparison'!B5,"") -> 0.92408907 | C7: =IFERROR(('Year 1 scenario comparison'!C5-'Year 1 scenario comparison'!C6)/'Year 1 scenario comparison'!C5,"") -> 0.27855711 | D7: =IFERROR(('Year 1 scenario comparison'!D5-'Year 1 scenario comparison'!D6)/'Year 1 scenario comparison'!D5,"") -> 0.90309096
A8: NS Year 1 operating profit | B8: =SUM('Runway and operating profit'!B10,'Runway and operating profit'!C10,'Runway and operating profit'!D10,'Runway and operating profit'!E10,'Runway and operating profit'!F10,'Runway and operating profit'!G10,'Runway and operating profit'!H10,'Runway and operating profit'!I10,'Runway and operating profit'!J10,'Runway and operating profit'!K10,'Runway and operating profit'!L10,'Runway and operating profit'!M10) -> 2288790 | C8: =SUM('Model inputs'!N31,'Model inputs'!O31,'Model inputs'!P31,'Model inputs'!Q31,'Model inputs'!R31,'Model inputs'!S31,'Model inputs'!T31,'Model inputs'!U31,'Model inputs'!V31,'Model inputs'!W31,'Model inputs'!X31,'Model inputs'!Y31) -> -142950 | D8: =SUM('Model inputs'!N30,'Model inputs'!O30,'Model inputs'!P30,'Model inputs'!Q30,'Model inputs'!R30,'Model inputs'!S30,'Model inputs'!T30,'Model inputs'!U30,'Model inputs'!V30,'Model inputs'!W30,'Model inputs'!X30,'Model inputs'!Y30) -> 4101090
A9: NS starting cash runway months | B9: =IF(IF(IF(ISERROR('Year 1 scenario comparison'!B8<0),'Year 1 scenario comparison'!B8<0,IF('Year 1 scenario comparison'!B8="","",'Year 1 scenario comparison'!B8<0))="",FALSE,IF(ISERROR('Year 1 scenario comparison'!B8<0),'Year 1 scenario comparison'!B8<0,IF('Year 1 scenario comparison'!B8="","",'Year 1 scenario comparison'!B8<0))),'Pricing and editable planning i'!B17/(-'Year 1 scenario comparison'!B8/12),"") | C9: =IF(IF(IF(ISERROR('Year 1 scenario comparison'!C8<0),'Year 1 scenario comparison'!C8<0,IF('Year 1 scenario comparison'!C8="","",'Year 1 scenario comparison'!C8<0))="",FALSE,IF(ISERROR('Year 1 scenario comparison'!C8<0),'Year 1 scenario comparison'!C8<0,IF('Year 1 scenario comparison'!C8="","",'Year 1 scenario comparison'!C8<0))),'Model inputs'!B42/(-'Year 1 scenario comparison'!C8/12),"") -> 25.183631 | D9: =IF(IF(IF(ISERROR('Year 1 scenario comparison'!D8<0),'Year 1 scenario comparison'!D8<0,IF('Year 1 scenario comparison'!D8="","",'Year 1 scenario comparison'!D8<0))="",FALSE,IF(ISERROR('Year 1 scenario comparison'!D8<0),'Year 1 scenario comparison'!D8<0,IF('Year 1 scenario comparison'!D8="","",'Year 1 scenario comparison'!D8<0))),'Model inputs'!B41/(-'Year 1 scenario comparison'!D8/12),"")

Sheet Model inputs
A1: Model inputs
A2: Integration values are aggregated snapshots; raw source records are not included.
A4: Variables
A5: Variable / segment | B5: Value | C5: Value | D5: 2026-01 | E5: 2026-02 | F5: 2026-03 | G5: 2026-04 | H5: 2026-05 | I5: 2026-06 | J5: 2026-07 | K5: 2026-08 | L5: 2026-09 | M5: 2026-10 | N5: 2026-11 | O5: 2026-12 | P5: 2027-01 | Q5: 2027-02 | R5: 2027-03 | S5: 2027-04 | T5: 2027-05 | U5: 2027-06 | V5: 2027-07 | W5: 2027-08 | X5: 2027-09 | Y5: 2027-10 | Z5: 2027-11 | AA5: 2027-12
A6: Active free students · Year 1 totals and 45-cafe break-even | B6: ='Pricing and editable planning i'!B14 -> 1000
A7: Active free students · Monthly revenue and check costs | C7: ='Pricing and editable planning i'!B14 -> 1000
A8: API check price · Year 1 totals and 45-cafe break-even | B8: ='Pricing and editable planning i'!B7 -> 49
A9: API check price · Monthly revenue and check costs | C9: ='Pricing and editable planning i'!B7 -> 49
A10: Cafe monthly price · Year 1 totals and 45-cafe break-even | B10: ='Pricing and editable planning i'!B6 -> 499
A11: Cafe monthly price · Monthly revenue and check costs | C11: ='Pricing and editable planning i'!B6 -> 499
A12: Checks per cafe per month · Year 1 totals and 45-cafe break-even | B12: ='Pricing and editable planning i'!B13 -> 10
A13: Checks per cafe per month · Monthly revenue and check costs | C13: ='Pricing and editable planning i'!B13 -> 10
A14: Checks per free student per month · Year 1 totals and 45-cafe break-even | B14: ='Pricing and editable planning i'!B15 -> 3
A15: Checks per free student per month · Monthly revenue and check costs | C15: ='Pricing and editable planning i'!B15 -> 3
A16: Cost per check · Year 1 totals and 45-cafe break-even | B16: ='Model inputs'!B49+'Model inputs'!B48 -> 2.25
A17: Cost per check · Monthly revenue and check costs | C17: ='Model inputs'!B49+'Model inputs'!B48 -> 2.25
A18: Monthly non-check overhead · Year 1 totals and 45-cafe break-even | B18: ='Pricing and editable planning i'!B16 -> 14692.5
A19: Monthly non-check overhead · Runway and operating profit | C19: ='Pricing and editable planning i'!B16 -> 14692.5
A20: NS check costs · by · Year 1 totals and 45-cafe break-even · Main Scenario | D20: =SUM('Model inputs'!D22,'Model inputs'!D23,'Model inputs'!D24) -> 0 | E20: =SUM('Model inputs'!E22,'Model inputs'!E23,'Model inputs'!E24) -> 0 | F20: =SUM('Model inputs'!F22,'Model inputs'!F23,'Model inputs'!F24) -> 0 | G20: =SUM('Model inputs'!G22,'Model inputs'!G23,'Model inputs'!G24) -> 0 | H20: =SUM('Model inputs'!H22,'Model inputs'!H23,'Model inputs'!H24) -> 0 | I20: =SUM('Model inputs'!I22,'Model inputs'!I23,'Model inputs'!I24) -> 0 | J20: =SUM('Model inputs'!J22,'Model inputs'!J23,'Model inputs'!J24) -> 0 | K20: =SUM('Model inputs'!K22,'Model inputs'!K23,'Model inputs'!K24) -> 0 | ... AA20: =SUM('Model inputs'!AA22,'Model inputs'!AA23,'Model inputs'!AA24) -> 16875
A21: NS check costs | D21: =IF('Model inputs'!D20="","",'Model inputs'!D20) -> 0 | E21: =IF('Model inputs'!E20="","",'Model inputs'!E20) -> 0 | F21: =IF('Model inputs'!F20="","",'Model inputs'!F20) -> 0 | G21: =IF('Model inputs'!G20="","",'Model inputs'!G20) -> 0 | H21: =IF('Model inputs'!H20="","",'Model inputs'!H20) -> 0 | I21: =IF('Model inputs'!I20="","",'Model inputs'!I20) -> 0 | J21: =IF('Model inputs'!J20="","",'Model inputs'!J20) -> 0 | K21: =IF('Model inputs'!K20="","",'Model inputs'!K20) -> 0 | ... AA21: =IF('Model inputs'!AA20="","",'Model inputs'!AA20) -> 16875
A22: NS check costs > API | D22: =0 -> 0 | E22: =0 -> 0 | F22: =0 -> 0 | G22: =0 -> 0 | H22: =0 -> 0 | I22: =0 -> 0 | J22: =0 -> 0 | K22: =0 -> 0 | L22: =0 -> 0 | M22: ='Model inputs'!M65*'Model inputs'!B16 -> 5625 | N22: ='Model inputs'!N51*'Model inputs'!B16 -> 5625 | O22: ='Model inputs'!O51*'Model inputs'!B16 -> 5625 | P22: ='Model inputs'!P51*'Model inputs'!B16 -> 5625 | Q22: ='Model inputs'!Q51*'Model inputs'!B16 -> 5625 | R22: ='Model inputs'!R51*'Model inputs'!B16 -> 5625 | S22: ='Model inputs'!S51*'Model inputs'!B16 -> 5625 | T22: ='Model inputs'!T51*'Model inputs'!B16 -> 5625 | U22: ='Model inputs'!U51*'Model inputs'!B16 -> 5625 | V22: ='Model inputs'!V51*'Model inputs'!B16 -> 5625 | W22: ='Model inputs'!W51*'Model inputs'!B16 -> 5625 | X22: ='Model inputs'!X51*'Model inputs'!B16 -> 5625 | Y22: ='Model inputs'!Y51*'Model inputs'!B16 -> 5625 | Z22: ='Model inputs'!Z65*'Model inputs'!B16 -> 5625 | AA22: ='Model inputs'!AA65*'Model inputs'!B16 -> 5625
A23: NS check costs > Cyber-cafes | D23: =0 -> 0 | E23: =0 -> 0 | F23: =0 -> 0 | G23: =0 -> 0 | H23: =0 -> 0 | I23: =0 -> 0 | J23: =0 -> 0 | K23: =0 -> 0 | L23: =0 -> 0 | M23: ='Model inputs'!M66*'Model inputs'!B16 -> 4500 | N23: ='Model inputs'!N52*'Model inputs'!B16 -> 4500 | O23: ='Model inputs'!O52*'Model inputs'!B16 -> 4500 | P23: ='Model inputs'!P52*'Model inputs'!B16 -> 4500 | Q23: ='Model inputs'!Q52*'Model inputs'!B16 -> 4500 | R23: ='Model inputs'!R52*'Model inputs'!B16 -> 4500 | S23: ='Model inputs'!S52*'Model inputs'!B16 -> 4500 | T23: ='Model inputs'!T52*'Model inputs'!B16 -> 4500 | U23: ='Model inputs'!U52*'Model inputs'!B16 -> 4500 | V23: ='Model inputs'!V52*'Model inputs'!B16 -> 4500 | W23: ='Model inputs'!W52*'Model inputs'!B16 -> 4500 | X23: ='Model inputs'!X52*'Model inputs'!B16 -> 4500 | Y23: ='Model inputs'!Y52*'Model inputs'!B16 -> 4500 | Z23: ='Model inputs'!Z66*'Model inputs'!B16 -> 4500 | AA23: ='Model inputs'!AA66*'Model inputs'!B16 -> 4500
A24: NS check costs > Students | D24: =0 -> 0 | E24: =0 -> 0 | F24: =0 -> 0 | G24: =0 -> 0 | H24: =0 -> 0 | I24: =0 -> 0 | J24: =0 -> 0 | K24: =0 -> 0 | L24: =0 -> 0 | M24: ='Model inputs'!M67*'Model inputs'!B16 -> 6750 | N24: ='Model inputs'!N53*'Model inputs'!B16 -> 6750 | O24: ='Model inputs'!O53*'Model inputs'!B16 -> 6750 | P24: ='Model inputs'!P53*'Model inputs'!B16 -> 6750 | Q24: ='Model inputs'!Q53*'Model inputs'!B16 -> 6750 | R24: ='Model inputs'!R53*'Model inputs'!B16 -> 6750 | S24: ='Model inputs'!S53*'Model inputs'!B16 -> 6750 | T24: ='Model inputs'!T53*'Model inputs'!B16 -> 6750 | U24: ='Model inputs'!U53*'Model inputs'!B16 -> 6750 | V24: ='Model inputs'!V53*'Model inputs'!B16 -> 6750 | W24: ='Model inputs'!W53*'Model inputs'!B16 -> 6750 | X24: ='Model inputs'!X53*'Model inputs'!B16 -> 6750 | Y24: ='Model inputs'!Y53*'Model inputs'!B16 -> 6750 | Z24: ='Model inputs'!Z67*'Model inputs'!B16 -> 6750 | AA24: ='Model inputs'!AA67*'Model inputs'!B16 -> 6750
A25: NS check costs · NaukriShield — Upside | D25: =SUM('Model inputs'!D57,'Model inputs'!D58,'Model inputs'!D59) -> 0 | E25: =SUM('Model inputs'!E57,'Model inputs'!E58,'Model inputs'!E59) -> 0 | F25: =SUM('Model inputs'!F57,'Model inputs'!F58,'Model inputs'!F59) -> 0 | G25: =SUM('Model inputs'!G57,'Model inputs'!G58,'Model inputs'!G59) -> 0 | H25: =SUM('Model inputs'!H57,'Model inputs'!H58,'Model inputs'!H59) -> 0 | I25: =SUM('Model inputs'!I57,'Model inputs'!I58,'Model inputs'!I59) -> 0 | J25: =SUM('Model inputs'!J57,'Model inputs'!J58,'Model inputs'!J59) -> 0 | K25: =SUM('Model inputs'!K57,'Model inputs'!K58,'Model inputs'!K59) -> 0 | ... AA25: =SUM('Model inputs'!AA57,'Model inputs'!AA58,'Model inputs'!AA59) -> 38250
A26: NS check costs · NaukriShield — Downside | D26: =SUM('Model inputs'!D61,'Model inputs'!D62,'Model inputs'!D63) -> 0 | E26: =SUM('Model inputs'!E61,'Model inputs'!E62,'Model inputs'!E63) -> 0 | F26: =SUM('Model inputs'!F61,'Model inputs'!F62,'Model inputs'!F63) -> 0 | G26: =SUM('Model inputs'!G61,'Model inputs'!G62,'Model inputs'!G63) -> 0 | H26: =SUM('Model inputs'!H61,'Model inputs'!H62,'Model inputs'!H63) -> 0 | I26: =SUM('Model inputs'!I61,'Model inputs'!I62,'Model inputs'!I63) -> 0 | J26: =SUM('Model inputs'!J61,'Model inputs'!J62,'Model inputs'!J63) -> 0 | K26: =SUM('Model inputs'!K61,'Model inputs'!K62,'Model inputs'!K63) -> 0 | ... AA26: =SUM('Model inputs'!AA61,'Model inputs'!AA62,'Model inputs'!AA63) -> 7200
A27: NS closing cash | K27: 0 | L27: 0 | M27: ='Model inputs'!M28+'Model inputs'!M29 -> 190732.5 | N27: ='Model inputs'!N28+'Model inputs'!N29 -> 490732.5 | O27: ='Model inputs'!O28+'Model inputs'!O29 -> 681465 | P27: ='Model inputs'!P28+'Model inputs'!P29 -> 872197.5 | Q27: ='Model inputs'!Q28+'Model inputs'!Q29 -> 1062930 | R27: ='Model inputs'!R28+'Model inputs'!R29 -> 1253662.5 | S27: ='Model inputs'!S28+'Model inputs'!S29 -> 1444395 | T27: ='Model inputs'!T28+'Model inputs'!T29 -> 1635127.5 | ... Y27: ='Model inputs'!Y28+'Model inputs'!Y29 -> 2588790
A28: NS opening cash | L28: 0 | M28: =IF('Model inputs'!L27="","",'Model inputs'!L27) -> 0 | N28: =IF('Model inputs'!B39="","",'Model inputs'!B39) -> 300000 | O28: =IF('Model inputs'!N27="","",'Model inputs'!N27) -> 490732.5 | P28: =IF('Model inputs'!O27="","",'Model inputs'!O27) -> 681465 | Q28: =IF('Model inputs'!P27="","",'Model inputs'!P27) -> 872197.5 | R28: =IF('Model inputs'!Q27="","",'Model inputs'!Q27) -> 1062930 | S28: =IF('Model inputs'!R27="","",'Model inputs'!R27) -> 1253662.5 | T28: =IF('Model inputs'!S27="","",'Model inputs'!S27) -> 1444395 | U28: =IF('Model inputs'!T27="","",'Model inputs'!T27) -> 1635127.5 | V28: =IF('Model inputs'!U27="","",'Model inputs'!U27) -> 1825860 | ... Y28: =IF('Model inputs'!X27="","",'Model inputs'!X27) -> 2398057.5
A29: NS operating profit · Year 1 totals and 45-cafe break-even · Main Scenario | D29: 0 | E29: 0 | F29: 0 | G29: 0 | H29: 0 | I29: 0 | J29: 0 | K29: 0 | L29: 0 | M29: ='Model inputs'!M54-'Model inputs'!M55 -> 190732.5 | N29: ='Model inputs'!N54-'Model inputs'!N55 -> 190732.5 | O29: ='Model inputs'!O54-'Model inputs'!O55 -> 190732.5 | P29: ='Model inputs'!P54-'Model inputs'!P55 -> 190732.5 | Q29: ='Model inputs'!Q54-'Model inputs'!Q55 -> 190732.5 | R29: ='Model inputs'!R54-'Model inputs'!R55 -> 190732.5 | S29: ='Model inputs'!S54-'Model inputs'!S55 -> 190732.5 | T29: ='Model inputs'!T54-'Model inputs'!T55 -> 190732.5 | ... Y29: ='Model inputs'!Y54-'Model inputs'!Y55 -> 190732.5 | Z29: ='Model inputs'!Z68-'Model inputs'!Z71 -> 190732.5 | AA29: ='Model inputs'!AA68-'Model inputs'!AA71 -> 190732.5
A30: NS operating profit · NaukriShield — Upside | D30: 0 | E30: 0 | F30: 0 | G30: 0 | H30: 0 | I30: 0 | J30: 0 | K30: 0 | L30: 0 | M30: ='Model inputs'!M69-'Model inputs'!M72 -> 341757.5 | N30: ='Model inputs'!N69-'Model inputs'!N72 -> 341757.5 | O30: ='Model inputs'!O69-'Model inputs'!O72 -> 341757.5 | P30: ='Model inputs'!P69-'Model inputs'!P72 -> 341757.5 | Q30: ='Model inputs'!Q69-'Model inputs'!Q72 -> 341757.5 | R30: ='Model inputs'!R69-'Model inputs'!R72 -> 341757.5 | S30: ='Model inputs'!S69-'Model inputs'!S72 -> 341757.5 | T30: ='Model inputs'!T69-'Model inputs'!T72 -> 341757.5 | ... AA30: ='Model inputs'!AA69-'Model inputs'!AA72 -> 341757.5
A31: NS operating profit · NaukriShield — Downside | D31: 0 | E31: 0 | F31: 0 | G31: 0 | H31: 0 | I31: 0 | J31: 0 | K31: 0 | L31: 0 | M31: ='Model inputs'!M70-'Model inputs'!M73 -> -11912.5 | N31: ='Model inputs'!N70-'Model inputs'!N73 -> -11912.5 | O31: ='Model inputs'!O70-'Model inputs'!O73 -> -11912.5 | P31: ='Model inputs'!P70-'Model inputs'!P73 -> -11912.5 | Q31: ='Model inputs'!Q70-'Model inputs'!Q73 -> -11912.5 | R31: ='Model inputs'!R70-'Model inputs'!R73 -> -11912.5 | S31: ='Model inputs'!S70-'Model inputs'!S73 -> -11912.5 | T31: ='Model inputs'!T70-'Model inputs'!T73 -> -11912.5 | ... AA31: ='Model inputs'!AA70-'Model inputs'!AA73 -> -11912.5
A32: NS revenue · by · Year 1 totals and 45-cafe break-even · Main Scenario | D32: =SUM('Model inputs'!D34,'Model inputs'!D35,'Model inputs'!D36) -> 0 | E32: =SUM('Model inputs'!E34,'Model inputs'!E35,'Model inputs'!E36) -> 0 | F32: =SUM('Model inputs'!F34,'Model inputs'!F35,'Model inputs'!F36) -> 0 | G32: =SUM('Model inputs'!G34,'Model inputs'!G35,'Model inputs'!G36) -> 0 | H32: =SUM('Model inputs'!H34,'Model inputs'!H35,'Model inputs'!H36) -> 0 | I32: =SUM('Model inputs'!I34,'Model inputs'!I35,'Model inputs'!I36) -> 0 | J32: =SUM('Model inputs'!J34,'Model inputs'!J35,'Model inputs'!J36) -> 0 | K32: =SUM('Model inputs'!K34,'Model inputs'!K35,'Model inputs'!K36) -> 0 | ... AA32: =SUM('Model inputs'!AA34,'Model inputs'!AA35,'Model inputs'!AA36) -> 222300
A33: NS revenue | D33: =IF('Model inputs'!D32="","",'Model inputs'!D32) -> 0 | E33: =IF('Model inputs'!E32="","",'Model inputs'!E32) -> 0 | F33: =IF('Model inputs'!F32="","",'Model inputs'!F32) -> 0 | G33: =IF('Model inputs'!G32="","",'Model inputs'!G32) -> 0 | H33: =IF('Model inputs'!H32="","",'Model inputs'!H32) -> 0 | I33: =IF('Model inputs'!I32="","",'Model inputs'!I32) -> 0 | J33: =IF('Model inputs'!J32="","",'Model inputs'!J32) -> 0 | K33: =IF('Model inputs'!K32="","",'Model inputs'!K32) -> 0 | ... AA33: =IF('Model inputs'!AA32="","",'Model inputs'!AA32) -> 222300
A34: NS revenue > API | D34: =0 -> 0 | E34: =0 -> 0 | F34: =0 -> 0 | G34: =0 -> 0 | H34: =0 -> 0 | I34: =0 -> 0 | J34: =0 -> 0 | K34: =0 -> 0 | L34: =0 -> 0 | M34: =IF(EXACT("API","Cyber-cafes"),'Model inputs'!C43*'Model inputs'!B10,IF(EXACT("API","API"),'Model inputs'!B46/12*'Model inputs'!B8,0)) -> 122500 | N34: =IF(EXACT("API","Cyber-cafes"),'Model inputs'!C43*'Model inputs'!B10,IF(EXACT("API","API"),'Model inputs'!B46/12*'Model inputs'!B8,0)) -> 122500 | O34: =IF(EXACT("API","Cyber-cafes"),'Model inputs'!C43*'Model inputs'!B10,IF(EXACT("API","API"),'Model inputs'!B46/12*'Model inputs'!B8,0)) -> 122500 | P34: =IF(EXACT("API","Cyber-cafes"),'Model inputs'!C43*'Model inputs'!B10,IF(EXACT("API","API"),'Model inputs'!B46/12*'Model inputs'!B8,0)) -> 122500 | Q34: =IF(EXACT("API","Cyber-cafes"),'Model inputs'!C43*'Model inputs'!B10,IF(EXACT("API","API"),'Model inputs'!B46/12*'Model inputs'!B8,0)) -> 122500 | R34: =IF(EXACT("API","Cyber-cafes"),'Model inputs'!C43*'Model inputs'!B10,IF(EXACT("API","API"),'Model inputs'!B46/12*'Model inputs'!B8,0)) -> 122500 | S34: =IF(EXACT("API","Cyber-cafes"),'Model inputs'!C43*'Model inputs'!B10,IF(EXACT("API","API"),'Model inputs'!B46/12*'Model inputs'!B8,0)) -> 122500 | T34: =IF(EXACT("API","Cyber-cafes"),'Model inputs'!C43*'Model inputs'!B10,IF(EXACT("API","API"),'Model inputs'!B46/12*'Model inputs'!B8,0)) -> 122500 | U34: =IF(EXACT("API","Cyber-cafes"),'Model inputs'!C43*'Model inputs'!B10,IF(EXACT("API","API"),'Model inputs'!B46/12*'Model inputs'!B8,0)) -> 122500 | V34: =IF(EXACT("API","Cyber-cafes"),'Model inputs'!C43*'Model inputs'!B10,IF(EXACT("API","API"),'Model inputs'!B46/12*'Model inputs'!B8,0)) -> 122500 | W34: =IF(EXACT("API","Cyber-cafes"),'Model inputs'!C43*'Model inputs'!B10,IF(EXACT("API","API"),'Model inputs'!B46/12*'Model inputs'!B8,0)) -> 122500 | X34: =IF(EXACT("API","Cyber-cafes"),'Model inputs'!C43*'Model inputs'!B10,IF(EXACT("API","API"),'Model inputs'!B46/12*'Model inputs'!B8,0)) -> 122500 | Y34: =IF(EXACT("API","Cyber-cafes"),'Model inputs'!C43*'Model inputs'!B10,IF(EXACT("API","API"),'Model inputs'!B46/12*'Model inputs'!B8,0)) -> 122500 | Z34: =IF(EXACT("API","Cyber-cafes"),'Model inputs'!C43*'Model inputs'!B10,IF(EXACT("API","API"),'Model inputs'!B46/12*'Model inputs'!B8,0)) -> 122500 | AA34: =IF(EXACT("API","Cyber-cafes"),'Model inputs'!C43*'Model inputs'!B10,IF(EXACT("API","API"),'Model inputs'!B46/12*'Model inputs'!B8,0)) -> 122500
A35: NS revenue > Cyber-cafes | D35: =0 -> 0 | E35: =0 -> 0 | F35: =0 -> 0 | G35: =0 -> 0 | H35: =0 -> 0 | I35: =0 -> 0 | J35: =0 -> 0 | K35: =0 -> 0 | L35: =0 -> 0 | M35: =IF(EXACT("Cyber-cafes","Cyber-cafes"),'Model inputs'!C43*'Model inputs'!B10,IF(EXACT("Cyber-cafes","API"),'Model inputs'!B46/12*'Model inputs'!B8,0)) -> 99800 | N35: =IF(EXACT("Cyber-cafes","Cyber-cafes"),'Model inputs'!C43*'Model inputs'!B10,IF(EXACT("Cyber-cafes","API"),'Model inputs'!B46/12*'Model inputs'!B8,0)) -> 99800 | O35: =IF(EXACT("Cyber-cafes","Cyber-cafes"),'Model inputs'!C43*'Model inputs'!B10,IF(EXACT("Cyber-cafes","API"),'Model inputs'!B46/12*'Model inputs'!B8,0)) -> 99800 | P35: =IF(EXACT("Cyber-cafes","Cyber-cafes"),'Model inputs'!C43*'Model inputs'!B10,IF(EXACT("Cyber-cafes","API"),'Model inputs'!B46/12*'Model inputs'!B8,0)) -> 99800 | Q35: =IF(EXACT("Cyber-cafes","Cyber-cafes"),'Model inputs'!C43*'Model inputs'!B10,IF(EXACT("Cyber-cafes","API"),'Model inputs'!B46/12*'Model inputs'!B8,0)) -> 99800 | R35: =IF(EXACT("Cyber-cafes","Cyber-cafes"),'Model inputs'!C43*'Model inputs'!B10,IF(EXACT("Cyber-cafes","API"),'Model inputs'!B46/12*'Model inputs'!B8,0)) -> 99800 | S35: =IF(EXACT("Cyber-cafes","Cyber-cafes"),'Model inputs'!C43*'Model inputs'!B10,IF(EXACT("Cyber-cafes","API"),'Model inputs'!B46/12*'Model inputs'!B8,0)) -> 99800 | T35: =IF(EXACT("Cyber-cafes","Cyber-cafes"),'Model inputs'!C43*'Model inputs'!B10,IF(EXACT("Cyber-cafes","API"),'Model inputs'!B46/12*'Model inputs'!B8,0)) -> 99800 | U35: =IF(EXACT("Cyber-cafes","Cyber-cafes"),'Model inputs'!C43*'Model inputs'!B10,IF(EXACT("Cyber-cafes","API"),'Model inputs'!B46/12*'Model inputs'!B8,0)) -> 99800 | V35: =IF(EXACT("Cyber-cafes","Cyber-cafes"),'Model inputs'!C43*'Model inputs'!B10,IF(EXACT("Cyber-cafes","API"),'Model inputs'!B46/12*'Model inputs'!B8,0)) -> 99800 | W35: =IF(EXACT("Cyber-cafes","Cyber-cafes"),'Model inputs'!C43*'Model inputs'!B10,IF(EXACT("Cyber-cafes","API"),'Model inputs'!B46/12*'Model inputs'!B8,0)) -> 99800 | X35: =IF(EXACT("Cyber-cafes","Cyber-cafes"),'Model inputs'!C43*'Model inputs'!B10,IF(EXACT("Cyber-cafes","API"),'Model inputs'!B46/12*'Model inputs'!B8,0)) -> 99800 | Y35: =IF(EXACT("Cyber-cafes","Cyber-cafes"),'Model inputs'!C43*'Model inputs'!B10,IF(EXACT("Cyber-cafes","API"),'Model inputs'!B46/12*'Model inputs'!B8,0)) -> 99800 | Z35: =IF(EXACT("Cyber-cafes","Cyber-cafes"),'Model inputs'!C43*'Model inputs'!B10,IF(EXACT("Cyber-cafes","API"),'Model inputs'!B46/12*'Model inputs'!B8,0)) -> 99800 | AA35: =IF(EXACT("Cyber-cafes","Cyber-cafes"),'Model inputs'!C43*'Model inputs'!B10,IF(EXACT("Cyber-cafes","API"),'Model inputs'!B46/12*'Model inputs'!B8,0)) -> 99800
A36: NS revenue > Students | D36: =0 -> 0 | E36: =0 -> 0 | F36: =0 -> 0 | G36: =0 -> 0 | H36: =0 -> 0 | I36: =0 -> 0 | J36: =0 -> 0 | K36: =0 -> 0 | L36: =0 -> 0 | M36: =IF(EXACT("Students","Cyber-cafes"),'Model inputs'!C43*'Model inputs'!B10,IF(EXACT("Students","API"),'Model inputs'!B46/12*'Model inputs'!B8,0)) -> 0 | N36: =IF(EXACT("Students","Cyber-cafes"),'Model inputs'!C43*'Model inputs'!B10,IF(EXACT("Students","API"),'Model inputs'!B46/12*'Model inputs'!B8,0)) -> 0 | O36: =IF(EXACT("Students","Cyber-cafes"),'Model inputs'!C43*'Model inputs'!B10,IF(EXACT("Students","API"),'Model inputs'!B46/12*'Model inputs'!B8,0)) -> 0 | P36: =IF(EXACT("Students","Cyber-cafes"),'Model inputs'!C43*'Model inputs'!B10,IF(EXACT("Students","API"),'Model inputs'!B46/12*'Model inputs'!B8,0)) -> 0 | Q36: =IF(EXACT("Students","Cyber-cafes"),'Model inputs'!C43*'Model inputs'!B10,IF(EXACT("Students","API"),'Model inputs'!B46/12*'Model inputs'!B8,0)) -> 0 | R36: =IF(EXACT("Students","Cyber-cafes"),'Model inputs'!C43*'Model inputs'!B10,IF(EXACT("Students","API"),'Model inputs'!B46/12*'Model inputs'!B8,0)) -> 0 | S36: =IF(EXACT("Students","Cyber-cafes"),'Model inputs'!C43*'Model inputs'!B10,IF(EXACT("Students","API"),'Model inputs'!B46/12*'Model inputs'!B8,0)) -> 0 | T36: =IF(EXACT("Students","Cyber-cafes"),'Model inputs'!C43*'Model inputs'!B10,IF(EXACT("Students","API"),'Model inputs'!B46/12*'Model inputs'!B8,0)) -> 0 | U36: =IF(EXACT("Students","Cyber-cafes"),'Model inputs'!C43*'Model inputs'!B10,IF(EXACT("Students","API"),'Model inputs'!B46/12*'Model inputs'!B8,0)) -> 0 | V36: =IF(EXACT("Students","Cyber-cafes"),'Model inputs'!C43*'Model inputs'!B10,IF(EXACT("Students","API"),'Model inputs'!B46/12*'Model inputs'!B8,0)) -> 0 | W36: =IF(EXACT("Students","Cyber-cafes"),'Model inputs'!C43*'Model inputs'!B10,IF(EXACT("Students","API"),'Model inputs'!B46/12*'Model inputs'!B8,0)) -> 0 | X36: =IF(EXACT("Students","Cyber-cafes"),'Model inputs'!C43*'Model inputs'!B10,IF(EXACT("Students","API"),'Model inputs'!B46/12*'Model inputs'!B8,0)) -> 0 | Y36: =IF(EXACT("Students","Cyber-cafes"),'Model inputs'!C43*'Model inputs'!B10,IF(EXACT("Students","API"),'Model inputs'!B46/12*'Model inputs'!B8,0)) -> 0 | Z36: =IF(EXACT("Students","Cyber-cafes"),'Model inputs'!C43*'Model inputs'!B10,IF(EXACT("Students","API"),'Model inputs'!B46/12*'Model inputs'!B8,0)) -> 0 | AA36: =IF(EXACT("Students","Cyber-cafes"),'Model inputs'!C43*'Model inputs'!B10,IF(EXACT("Students","API"),'Model inputs'!B46/12*'Model inputs'!B8,0)) -> 0
A37: NS revenue · NaukriShield — Upside | D37: =SUM('Model inputs'!D75,'Model inputs'!D76,'Model inputs'!D77) -> 0 | E37: =SUM('Model inputs'!E75,'Model inputs'!E76,'Model inputs'!E77) -> 0 | F37: =SUM('Model inputs'!F75,'Model inputs'!F76,'Model inputs'!F77) -> 0 | G37: =SUM('Model inputs'!G75,'Model inputs'!G76,'Model inputs'!G77) -> 0 | H37: =SUM('Model inputs'!H75,'Model inputs'!H76,'Model inputs'!H77) -> 0 | I37: =SUM('Model inputs'!I75,'Model inputs'!I76,'Model inputs'!I77) -> 0 | J37: =SUM('Model inputs'!J75,'Model inputs'!J76,'Model inputs'!J77) -> 0 | K37: =SUM('Model inputs'!K75,'Model inputs'!K76,'Model inputs'!K77) -> 0 | ... AA37: =SUM('Model inputs'!AA75,'Model inputs'!AA76,'Model inputs'!AA77) -> 394700
A38: NS revenue · NaukriShield — Downside | D38: =SUM('Model inputs'!D79,'Model inputs'!D80,'Model inputs'!D81) -> 0 | E38: =SUM('Model inputs'!E79,'Model inputs'!E80,'Model inputs'!E81) -> 0 | F38: =SUM('Model inputs'!F79,'Model inputs'!F80,'Model inputs'!F81) -> 0 | G38: =SUM('Model inputs'!G79,'Model inputs'!G80,'Model inputs'!G81) -> 0 | H38: =SUM('Model inputs'!H79,'Model inputs'!H80,'Model inputs'!H81) -> 0 | I38: =SUM('Model inputs'!I79,'Model inputs'!I80,'Model inputs'!I81) -> 0 | J38: =SUM('Model inputs'!J79,'Model inputs'!J80,'Model inputs'!J81) -> 0 | K38: =SUM('Model inputs'!K79,'Model inputs'!K80,'Model inputs'!K81) -> 0 | ... AA38: =SUM('Model inputs'!AA79,'Model inputs'!AA80,'Model inputs'!AA81) -> 9980
A39: Opening cash assumption · Year 1 totals and 45-cafe break-even · Main Scenario | B39: ='Pricing and editable planning i'!B17 -> 300000
A40: Opening cash assumption · Runway and operating profit · Main Scenario | C40: ='Pricing and editable planning i'!B17 -> 300000
A41: Opening cash assumption · NaukriShield — Upside | B41: ='Pricing and editable planning i'!B17 -> 300000
A42: Opening cash assumption · NaukriShield — Downside | B42: ='Pricing and editable planning i'!B17 -> 300000
A43: Paying cafes · Monthly revenue and check costs | C43: ='Pricing and editable planning i'!B11 -> 200
A44: Student monthly free allowance · Year 1 totals and 45-cafe break-even | B44: ='Pricing and editable planning i'!B5 -> 3
A45: Student monthly free allowance · Monthly revenue and check costs | C45: ='Pricing and editable planning i'!B5 -> 3
A46: Year 1 API checks · Year 1 totals and 45-cafe break-even | B46: ='Pricing and editable planning i'!B12 -> 30000
A47: Year 1 API checks · Monthly revenue and check costs | C47: ='Pricing and editable planning i'!B12 -> 30000
A48: Cached data cost per check · Pricing and editable planning inputs | B48: ='Pricing and editable planning i'!B9 -> 1.5
A49: Haiku cost per check · Pricing and editable planning inputs | B49: ='Pricing and editable planning i'!B8 -> 0.75
A50: NS checks | N50: =SUM('Model inputs'!N51,'Model inputs'!N52,'Model inputs'!N53) -> 7500 | O50: =SUM('Model inputs'!O51,'Model inputs'!O52,'Model inputs'!O53) -> 7500 | P50: =SUM('Model inputs'!P51,'Model inputs'!P52,'Model inputs'!P53) -> 7500 | Q50: =SUM('Model inputs'!Q51,'Model inputs'!Q52,'Model inputs'!Q53) -> 7500 | R50: =SUM('Model inputs'!R51,'Model inputs'!R52,'Model inputs'!R53) -> 7500 | S50: =SUM('Model inputs'!S51,'Model inputs'!S52,'Model inputs'!S53) -> 7500 | T50: =SUM('Model inputs'!T51,'Model inputs'!T52,'Model inputs'!T53) -> 7500 | U50: =SUM('Model inputs'!U51,'Model inputs'!U52,'Model inputs'!U53) -> 7500 | ... Y50: =SUM('Model inputs'!Y51,'Model inputs'!Y52,'Model inputs'!Y53) -> 7500
A51: NS checks > API | N51: =IF(EXACT("API","Cyber-cafes"),'Model inputs'!C43*'Model inputs'!B12,IF(EXACT("API","API"),'Model inputs'!B46/12,'Model inputs'!B6*MIN('Model inputs'!B14,'Model inputs'!B44))) -> 2500 | O51: =IF(EXACT("API","Cyber-cafes"),'Model inputs'!C43*'Model inputs'!B12,IF(EXACT("API","API"),'Model inputs'!B46/12,'Model inputs'!B6*MIN('Model inputs'!B14,'Model inputs'!B44))) -> 2500 | P51: =IF(EXACT("API","Cyber-cafes"),'Model inputs'!C43*'Model inputs'!B12,IF(EXACT("API","API"),'Model inputs'!B46/12,'Model inputs'!B6*MIN('Model inputs'!B14,'Model inputs'!B44))) -> 2500 | Q51: =IF(EXACT("API","Cyber-cafes"),'Model inputs'!C43*'Model inputs'!B12,IF(EXACT("API","API"),'Model inputs'!B46/12,'Model inputs'!B6*MIN('Model inputs'!B14,'Model inputs'!B44))) -> 2500 | R51: =IF(EXACT("API","Cyber-cafes"),'Model inputs'!C43*'Model inputs'!B12,IF(EXACT("API","API"),'Model inputs'!B46/12,'Model inputs'!B6*MIN('Model inputs'!B14,'Model inputs'!B44))) -> 2500 | S51: =IF(EXACT("API","Cyber-cafes"),'Model inputs'!C43*'Model inputs'!B12,IF(EXACT("API","API"),'Model inputs'!B46/12,'Model inputs'!B6*MIN('Model inputs'!B14,'Model inputs'!B44))) -> 2500 | T51: =IF(EXACT("API","Cyber-cafes"),'Model inputs'!C43*'Model inputs'!B12,IF(EXACT("API","API"),'Model inputs'!B46/12,'Model inputs'!B6*MIN('Model inputs'!B14,'Model inputs'!B44))) -> 2500 | U51: =IF(EXACT("API","Cyber-cafes"),'Model inputs'!C43*'Model inputs'!B12,IF(EXACT("API","API"),'Model inputs'!B46/12,'Model inputs'!B6*MIN('Model inputs'!B14,'Model inputs'!B44))) -> 2500 | V51: =IF(EXACT("API","Cyber-cafes"),'Model inputs'!C43*'Model inputs'!B12,IF(EXACT("API","API"),'Model inputs'!B46/12,'Model inputs'!B6*MIN('Model inputs'!B14,'Model inputs'!B44))) -> 2500 | W51: =IF(EXACT("API","Cyber-cafes"),'Model inputs'!C43*'Model inputs'!B12,IF(EXACT("API","API"),'Model inputs'!B46/12,'Model inputs'!B6*MIN('Model inputs'!B14,'Model inputs'!B44))) -> 2500 | X51: =IF(EXACT("API","Cyber-cafes"),'Model inputs'!C43*'Model inputs'!B12,IF(EXACT("API","API"),'Model inputs'!B46/12,'Model inputs'!B6*MIN('Model inputs'!B14,'Model inputs'!B44))) -> 2500 | Y51: =IF(EXACT("API","Cyber-cafes"),'Model inputs'!C43*'Model inputs'!B12,IF(EXACT("API","API"),'Model inputs'!B46/12,'Model inputs'!B6*MIN('Model inputs'!B14,'Model inputs'!B44))) -> 2500
A52: NS checks > Cyber-cafes | N52: =IF(EXACT("Cyber-cafes","Cyber-cafes"),'Model inputs'!C43*'Model inputs'!B12,IF(EXACT("Cyber-cafes","API"),'Model inputs'!B46/12,'Model inputs'!B6*MIN('Model inputs'!B14,'Model inputs'!B44))) -> 2000 | O52: =IF(EXACT("Cyber-cafes","Cyber-cafes"),'Model inputs'!C43*'Model inputs'!B12,IF(EXACT("Cyber-cafes","API"),'Model inputs'!B46/12,'Model inputs'!B6*MIN('Model inputs'!B14,'Model inputs'!B44))) -> 2000 | P52: =IF(EXACT("Cyber-cafes","Cyber-cafes"),'Model inputs'!C43*'Model inputs'!B12,IF(EXACT("Cyber-cafes","API"),'Model inputs'!B46/12,'Model inputs'!B6*MIN('Model inputs'!B14,'Model inputs'!B44))) -> 2000 | Q52: =IF(EXACT("Cyber-cafes","Cyber-cafes"),'Model inputs'!C43*'Model inputs'!B12,IF(EXACT("Cyber-cafes","API"),'Model inputs'!B46/12,'Model inputs'!B6*MIN('Model inputs'!B14,'Model inputs'!B44))) -> 2000 | R52: =IF(EXACT("Cyber-cafes","Cyber-cafes"),'Model inputs'!C43*'Model inputs'!B12,IF(EXACT("Cyber-cafes","API"),'Model inputs'!B46/12,'Model inputs'!B6*MIN('Model inputs'!B14,'Model inputs'!B44))) -> 2000 | S52: =IF(EXACT("Cyber-cafes","Cyber-cafes"),'Model inputs'!C43*'Model inputs'!B12,IF(EXACT("Cyber-cafes","API"),'Model inputs'!B46/12,'Model inputs'!B6*MIN('Model inputs'!B14,'Model inputs'!B44))) -> 2000 | T52: =IF(EXACT("Cyber-cafes","Cyber-cafes"),'Model inputs'!C43*'Model inputs'!B12,IF(EXACT("Cyber-cafes","API"),'Model inputs'!B46/12,'Model inputs'!B6*MIN('Model inputs'!B14,'Model inputs'!B44))) -> 2000 | U52: =IF(EXACT("Cyber-cafes","Cyber-cafes"),'Model inputs'!C43*'Model inputs'!B12,IF(EXACT("Cyber-cafes","API"),'Model inputs'!B46/12,'Model inputs'!B6*MIN('Model inputs'!B14,'Model inputs'!B44))) -> 2000 | V52: =IF(EXACT("Cyber-cafes","Cyber-cafes"),'Model inputs'!C43*'Model inputs'!B12,IF(EXACT("Cyber-cafes","API"),'Model inputs'!B46/12,'Model inputs'!B6*MIN('Model inputs'!B14,'Model inputs'!B44))) -> 2000 | W52: =IF(EXACT("Cyber-cafes","Cyber-cafes"),'Model inputs'!C43*'Model inputs'!B12,IF(EXACT("Cyber-cafes","API"),'Model inputs'!B46/12,'Model inputs'!B6*MIN('Model inputs'!B14,'Model inputs'!B44))) -> 2000 | X52: =IF(EXACT("Cyber-cafes","Cyber-cafes"),'Model inputs'!C43*'Model inputs'!B12,IF(EXACT("Cyber-cafes","API"),'Model inputs'!B46/12,'Model inputs'!B6*MIN('Model inputs'!B14,'Model inputs'!B44))) -> 2000 | Y52: =IF(EXACT("Cyber-cafes","Cyber-cafes"),'Model inputs'!C43*'Model inputs'!B12,IF(EXACT("Cyber-cafes","API"),'Model inputs'!B46/12,'Model inputs'!B6*MIN('Model inputs'!B14,'Model inputs'!B44))) -> 2000
A53: NS checks > Students | N53: =IF(EXACT("Students","Cyber-cafes"),'Model inputs'!C43*'Model inputs'!B12,IF(EXACT("Students","API"),'Model inputs'!B46/12,'Model inputs'!B6*MIN('Model inputs'!B14,'Model inputs'!B44))) -> 3000 | O53: =IF(EXACT("Students","Cyber-cafes"),'Model inputs'!C43*'Model inputs'!B12,IF(EXACT("Students","API"),'Model inputs'!B46/12,'Model inputs'!B6*MIN('Model inputs'!B14,'Model inputs'!B44))) -> 3000 | P53: =IF(EXACT("Students","Cyber-cafes"),'Model inputs'!C43*'Model inputs'!B12,IF(EXACT("Students","API"),'Model inputs'!B46/12,'Model inputs'!B6*MIN('Model inputs'!B14,'Model inputs'!B44))) -> 3000 | Q53: =IF(EXACT("Students","Cyber-cafes"),'Model inputs'!C43*'Model inputs'!B12,IF(EXACT("Students","API"),'Model inputs'!B46/12,'Model inputs'!B6*MIN('Model inputs'!B14,'Model inputs'!B44))) -> 3000 | R53: =IF(EXACT("Students","Cyber-cafes"),'Model inputs'!C43*'Model inputs'!B12,IF(EXACT("Students","API"),'Model inputs'!B46/12,'Model inputs'!B6*MIN('Model inputs'!B14,'Model inputs'!B44))) -> 3000 | S53: =IF(EXACT("Students","Cyber-cafes"),'Model inputs'!C43*'Model inputs'!B12,IF(EXACT("Students","API"),'Model inputs'!B46/12,'Model inputs'!B6*MIN('Model inputs'!B14,'Model inputs'!B44))) -> 3000 | T53: =IF(EXACT("Students","Cyber-cafes"),'Model inputs'!C43*'Model inputs'!B12,IF(EXACT("Students","API"),'Model inputs'!B46/12,'Model inputs'!B6*MIN('Model inputs'!B14,'Model inputs'!B44))) -> 3000 | U53: =IF(EXACT("Students","Cyber-cafes"),'Model inputs'!C43*'Model inputs'!B12,IF(EXACT("Students","API"),'Model inputs'!B46/12,'Model inputs'!B6*MIN('Model inputs'!B14,'Model inputs'!B44))) -> 3000 | V53: =IF(EXACT("Students","Cyber-cafes"),'Model inputs'!C43*'Model inputs'!B12,IF(EXACT("Students","API"),'Model inputs'!B46/12,'Model inputs'!B6*MIN('Model inputs'!B14,'Model inputs'!B44))) -> 3000 | W53: =IF(EXACT("Students","Cyber-cafes"),'Model inputs'!C43*'Model inputs'!B12,IF(EXACT("Students","API"),'Model inputs'!B46/12,'Model inputs'!B6*MIN('Model inputs'!B14,'Model inputs'!B44))) -> 3000 | X53: =IF(EXACT("Students","Cyber-cafes"),'Model inputs'!C43*'Model inputs'!B12,IF(EXACT("Students","API"),'Model inputs'!B46/12,'Model inputs'!B6*MIN('Model inputs'!B14,'Model inputs'!B44))) -> 3000 | Y53: =IF(EXACT("Students","Cyber-cafes"),'Model inputs'!C43*'Model inputs'!B12,IF(EXACT("Students","API"),'Model inputs'!B46/12,'Model inputs'!B6*MIN('Model inputs'!B14,'Model inputs'!B44))) -> 3000
A54: NS gross profit · Runway and operating profit | K54: 0 | L54: 0 | M54: ='Model inputs'!M32-'Model inputs'!M20 -> 205425 | N54: ='Model inputs'!N32-'Model inputs'!N20 -> 205425 | O54: ='Model inputs'!O32-'Model inputs'!O20 -> 205425 | P54: ='Model inputs'!P32-'Model inputs'!P20 -> 205425 | Q54: ='Model inputs'!Q32-'Model inputs'!Q20 -> 205425 | R54: ='Model inputs'!R32-'Model inputs'!R20 -> 205425 | S54: ='Model inputs'!S32-'Model inputs'!S20 -> 205425 | T54: ='Model inputs'!T32-'Model inputs'!T20 -> 205425 | ... Y54: ='Model inputs'!Y32-'Model inputs'!Y20 -> 205425
A55: NS overhead · Runway and operating profit | K55: 0 | L55: 0 | M55: =IF('Model inputs'!B18="","",'Model inputs'!B18) -> 14692.5 | N55: =IF('Model inputs'!B18="","",'Model inputs'!B18) -> 14692.5 | O55: =IF('Model inputs'!B18="","",'Model inputs'!B18) -> 14692.5 | P55: =IF('Model inputs'!B18="","",'Model inputs'!B18) -> 14692.5 | Q55: =IF('Model inputs'!B18="","",'Model inputs'!B18) -> 14692.5 | R55: =IF('Model inputs'!B18="","",'Model inputs'!B18) -> 14692.5 | S55: =IF('Model inputs'!B18="","",'Model inputs'!B18) -> 14692.5 | T55: =IF('Model inputs'!B18="","",'Model inputs'!B18) -> 14692.5 | U55: =IF('Model inputs'!B18="","",'Model inputs'!B18) -> 14692.5 | V55: =IF('Model inputs'!B18="","",'Model inputs'!B18) -> 14692.5 | W55: =IF('Model inputs'!B18="","",'Model inputs'!B18) -> 14692.5 | X55: =IF('Model inputs'!B18="","",'Model inputs'!B18) -> 14692.5 | Y55: =IF('Model inputs'!B18="","",'Model inputs'!B18) -> 14692.5
A56: NS check costs | D56: =IF('Model inputs'!D25="","",'Model inputs'!D25) -> 0 | E56: =IF('Model inputs'!E25="","",'Model inputs'!E25) -> 0 | F56: =IF('Model inputs'!F25="","",'Model inputs'!F25) -> 0 | G56: =IF('Model inputs'!G25="","",'Model inputs'!G25) -> 0 | H56: =IF('Model inputs'!H25="","",'Model inputs'!H25) -> 0 | I56: =IF('Model inputs'!I25="","",'Model inputs'!I25) -> 0 | J56: =IF('Model inputs'!J25="","",'Model inputs'!J25) -> 0 | K56: =IF('Model inputs'!K25="","",'Model inputs'!K25) -> 0 | ... AA56: =IF('Model inputs'!AA25="","",'Model inputs'!AA25) -> 38250
A57: NS check costs > API | D57: ='Model inputs'!D22 -> 0 | E57: ='Model inputs'!E22 -> 0 | F57: ='Model inputs'!F22 -> 0 | G57: ='Model inputs'!G22 -> 0 | H57: ='Model inputs'!H22 -> 0 | I57: ='Model inputs'!I22 -> 0 | J57: ='Model inputs'!J22 -> 0 | K57: ='Model inputs'!K22 -> 0 | L57: ='Model inputs'!L22 -> 0 | M57: ='Model inputs'!M93*'Model inputs'!C88 -> 11250 | N57: ='Model inputs'!N93*'Model inputs'!C88 -> 11250 | O57: ='Model inputs'!O93*'Model inputs'!C88 -> 11250 | P57: ='Model inputs'!P93*'Model inputs'!C88 -> 11250 | Q57: ='Model inputs'!Q93*'Model inputs'!C88 -> 11250 | R57: ='Model inputs'!R93*'Model inputs'!C88 -> 11250 | S57: ='Model inputs'!S93*'Model inputs'!C88 -> 11250 | T57: ='Model inputs'!T93*'Model inputs'!C88 -> 11250 | U57: ='Model inputs'!U93*'Model inputs'!C88 -> 11250 | V57: ='Model inputs'!V93*'Model inputs'!C88 -> 11250 | W57: ='Model inputs'!W93*'Model inputs'!C88 -> 11250 | X57: ='Model inputs'!X93*'Model inputs'!C88 -> 11250 | Y57: ='Model inputs'!Y93*'Model inputs'!C88 -> 11250 | Z57: ='Model inputs'!Z93*'Model inputs'!C88 -> 11250 | AA57: ='Model inputs'!AA93*'Model inputs'!C88 -> 11250
A58: NS check costs > Cyber-cafes | D58: ='Model inputs'!D23 -> 0 | E58: ='Model inputs'!E23 -> 0 | F58: ='Model inputs'!F23 -> 0 | G58: ='Model inputs'!G23 -> 0 | H58: ='Model inputs'!H23 -> 0 | I58: ='Model inputs'!I23 -> 0 | J58: ='Model inputs'!J23 -> 0 | K58: ='Model inputs'!K23 -> 0 | L58: ='Model inputs'!L23 -> 0 | M58: ='Model inputs'!M94*'Model inputs'!C88 -> 13500 | N58: ='Model inputs'!N94*'Model inputs'!C88 -> 13500 | O58: ='Model inputs'!O94*'Model inputs'!C88 -> 13500 | P58: ='Model inputs'!P94*'Model inputs'!C88 -> 13500 | Q58: ='Model inputs'!Q94*'Model inputs'!C88 -> 13500 | R58: ='Model inputs'!R94*'Model inputs'!C88 -> 13500 | S58: ='Model inputs'!S94*'Model inputs'!C88 -> 13500 | T58: ='Model inputs'!T94*'Model inputs'!C88 -> 13500 | U58: ='Model inputs'!U94*'Model inputs'!C88 -> 13500 | V58: ='Model inputs'!V94*'Model inputs'!C88 -> 13500 | W58: ='Model inputs'!W94*'Model inputs'!C88 -> 13500 | X58: ='Model inputs'!X94*'Model inputs'!C88 -> 13500 | Y58: ='Model inputs'!Y94*'Model inputs'!C88 -> 13500 | Z58: ='Model inputs'!Z94*'Model inputs'!C88 -> 13500 | AA58: ='Model inputs'!AA94*'Model inputs'!C88 -> 13500
A59: NS check costs > Students | D59: ='Model inputs'!D24 -> 0 | E59: ='Model inputs'!E24 -> 0 | F59: ='Model inputs'!F24 -> 0 | G59: ='Model inputs'!G24 -> 0 | H59: ='Model inputs'!H24 -> 0 | I59: ='Model inputs'!I24 -> 0 | J59: ='Model inputs'!J24 -> 0 | K59: ='Model inputs'!K24 -> 0 | L59: ='Model inputs'!L24 -> 0 | M59: ='Model inputs'!M95*'Model inputs'!C88 -> 13500 | N59: ='Model inputs'!N95*'Model inputs'!C88 -> 13500 | O59: ='Model inputs'!O95*'Model inputs'!C88 -> 13500 | P59: ='Model inputs'!P95*'Model inputs'!C88 -> 13500 | Q59: ='Model inputs'!Q95*'Model inputs'!C88 -> 13500 | R59: ='Model inputs'!R95*'Model inputs'!C88 -> 13500 | S59: ='Model inputs'!S95*'Model inputs'!C88 -> 13500 | T59: ='Model inputs'!T95*'Model inputs'!C88 -> 13500 | U59: ='Model inputs'!U95*'Model inputs'!C88 -> 13500 | V59: ='Model inputs'!V95*'Model inputs'!C88 -> 13500 | W59: ='Model inputs'!W95*'Model inputs'!C88 -> 13500 | X59: ='Model inputs'!X95*'Model inputs'!C88 -> 13500 | Y59: ='Model inputs'!Y95*'Model inputs'!C88 -> 13500 | Z59: ='Model inputs'!Z95*'Model inputs'!C88 -> 13500 | AA59: ='Model inputs'!AA95*'Model inputs'!C88 -> 13500
A60: NS check costs | D60: =IF('Model inputs'!D26="","",'Model inputs'!D26) -> 0 | E60: =IF('Model inputs'!E26="","",'Model inputs'!E26) -> 0 | F60: =IF('Model inputs'!F26="","",'Model inputs'!F26) -> 0 | G60: =IF('Model inputs'!G26="","",'Model inputs'!G26) -> 0 | H60: =IF('Model inputs'!H26="","",'Model inputs'!H26) -> 0 | I60: =IF('Model inputs'!I26="","",'Model inputs'!I26) -> 0 | J60: =IF('Model inputs'!J26="","",'Model inputs'!J26) -> 0 | K60: =IF('Model inputs'!K26="","",'Model inputs'!K26) -> 0 | ... AA60: =IF('Model inputs'!AA26="","",'Model inputs'!AA26) -> 7200
A61: NS check costs > API | D61: ='Model inputs'!D22 -> 0 | E61: ='Model inputs'!E22 -> 0 | F61: ='Model inputs'!F22 -> 0 | G61: ='Model inputs'!G22 -> 0 | H61: ='Model inputs'!H22 -> 0 | I61: ='Model inputs'!I22 -> 0 | J61: ='Model inputs'!J22 -> 0 | K61: ='Model inputs'!K22 -> 0 | L61: ='Model inputs'!L22 -> 0 | M61: ='Model inputs'!M97*'Model inputs'!C89 -> 0 | N61: ='Model inputs'!N97*'Model inputs'!C89 -> 0 | O61: ='Model inputs'!O97*'Model inputs'!C89 -> 0 | P61: ='Model inputs'!P97*'Model inputs'!C89 -> 0 | Q61: ='Model inputs'!Q97*'Model inputs'!C89 -> 0 | R61: ='Model inputs'!R97*'Model inputs'!C89 -> 0 | S61: ='Model inputs'!S97*'Model inputs'!C89 -> 0 | T61: ='Model inputs'!T97*'Model inputs'!C89 -> 0 | U61: ='Model inputs'!U97*'Model inputs'!C89 -> 0 | V61: ='Model inputs'!V97*'Model inputs'!C89 -> 0 | W61: ='Model inputs'!W97*'Model inputs'!C89 -> 0 | X61: ='Model inputs'!X97*'Model inputs'!C89 -> 0 | Y61: ='Model inputs'!Y97*'Model inputs'!C89 -> 0 | Z61: ='Model inputs'!Z97*'Model inputs'!C89 -> 0 | AA61: ='Model inputs'!AA97*'Model inputs'!C89 -> 0
A62: NS check costs > Cyber-cafes | D62: ='Model inputs'!D23 -> 0 | E62: ='Model inputs'!E23 -> 0 | F62: ='Model inputs'!F23 -> 0 | G62: ='Model inputs'!G23 -> 0 | H62: ='Model inputs'!H23 -> 0 | I62: ='Model inputs'!I23 -> 0 | J62: ='Model inputs'!J23 -> 0 | K62: ='Model inputs'!K23 -> 0 | L62: ='Model inputs'!L23 -> 0 | M62: ='Model inputs'!M98*'Model inputs'!C89 -> 450 | N62: ='Model inputs'!N98*'Model inputs'!C89 -> 450 | O62: ='Model inputs'!O98*'Model inputs'!C89 -> 450 | P62: ='Model inputs'!P98*'Model inputs'!C89 -> 450 | Q62: ='Model inputs'!Q98*'Model inputs'!C89 -> 450 | R62: ='Model inputs'!R98*'Model inputs'!C89 -> 450 | S62: ='Model inputs'!S98*'Model inputs'!C89 -> 450 | T62: ='Model inputs'!T98*'Model inputs'!C89 -> 450 | U62: ='Model inputs'!U98*'Model inputs'!C89 -> 450 | V62: ='Model inputs'!V98*'Model inputs'!C89 -> 450 | W62: ='Model inputs'!W98*'Model inputs'!C89 -> 450 | X62: ='Model inputs'!X98*'Model inputs'!C89 -> 450 | Y62: ='Model inputs'!Y98*'Model inputs'!C89 -> 450 | Z62: ='Model inputs'!Z98*'Model inputs'!C89 -> 450 | AA62: ='Model inputs'!AA98*'Model inputs'!C89 -> 450
A63: NS check costs > Students | D63: ='Model inputs'!D24 -> 0 | E63: ='Model inputs'!E24 -> 0 | F63: ='Model inputs'!F24 -> 0 | G63: ='Model inputs'!G24 -> 0 | H63: ='Model inputs'!H24 -> 0 | I63: ='Model inputs'!I24 -> 0 | J63: ='Model inputs'!J24 -> 0 | K63: ='Model inputs'!K24 -> 0 | L63: ='Model inputs'!L24 -> 0 | M63: ='Model inputs'!M99*'Model inputs'!C89 -> 6750 | N63: ='Model inputs'!N99*'Model inputs'!C89 -> 6750 | O63: ='Model inputs'!O99*'Model inputs'!C89 -> 6750 | P63: ='Model inputs'!P99*'Model inputs'!C89 -> 6750 | Q63: ='Model inputs'!Q99*'Model inputs'!C89 -> 6750 | R63: ='Model inputs'!R99*'Model inputs'!C89 -> 6750 | S63: ='Model inputs'!S99*'Model inputs'!C89 -> 6750 | T63: ='Model inputs'!T99*'Model inputs'!C89 -> 6750 | U63: ='Model inputs'!U99*'Model inputs'!C89 -> 6750 | V63: ='Model inputs'!V99*'Model inputs'!C89 -> 6750 | W63: ='Model inputs'!W99*'Model inputs'!C89 -> 6750 | X63: ='Model inputs'!X99*'Model inputs'!C89 -> 6750 | Y63: ='Model inputs'!Y99*'Model inputs'!C89 -> 6750 | Z63: ='Model inputs'!Z99*'Model inputs'!C89 -> 6750 | AA63: ='Model inputs'!AA99*'Model inputs'!C89 -> 6750
A64: NS checks | D64: =SUM('Model inputs'!D65,'Model inputs'!D66,'Model inputs'!D67) -> 0 | E64: =SUM('Model inputs'!E65,'Model inputs'!E66,'Model inputs'!E67) -> 0 | F64: =SUM('Model inputs'!F65,'Model inputs'!F66,'Model inputs'!F67) -> 0 | G64: =SUM('Model inputs'!G65,'Model inputs'!G66,'Model inputs'!G67) -> 0 | H64: =SUM('Model inputs'!H65,'Model inputs'!H66,'Model inputs'!H67) -> 0 | I64: =SUM('Model inputs'!I65,'Model inputs'!I66,'Model inputs'!I67) -> 0 | J64: =SUM('Model inputs'!J65,'Model inputs'!J66,'Model inputs'!J67) -> 0 | K64: =SUM('Model inputs'!K65,'Model inputs'!K66,'Model inputs'!K67) -> 0 | ... M64: =SUM('Model inputs'!M65,'Model inputs'!M66,'Model inputs'!M67) -> 7500 | N64: =IF('Model inputs'!N50="","",'Model inputs'!N50) -> 7500 | O64: =IF('Model inputs'!O50="","",'Model inputs'!O50) -> 7500 | P64: =IF('Model inputs'!P50="","",'Model inputs'!P50) -> 7500 | Q64: =IF('Model inputs'!Q50="","",'Model inputs'!Q50) -> 7500 | R64: =IF('Model inputs'!R50="","",'Model inputs'!R50) -> 7500 | S64: =IF('Model inputs'!S50="","",'Model inputs'!S50) -> 7500 | T64: =IF('Model inputs'!T50="","",'Model inputs'!T50) -> 7500 | U64: =IF('Model inputs'!U50="","",'Model inputs'!U50) -> 7500 | ... Y64: =IF('Model inputs'!Y50="","",'Model inputs'!Y50) -> 7500 | Z64: =SUM('Model inputs'!Z65,'Model inputs'!Z66,'Model inputs'!Z67) -> 7500 | AA64: =SUM('Model inputs'!AA65,'Model inputs'!AA66,'Model inputs'!AA67) -> 7500
A65: NS checks > API | D65: =0 -> 0 | E65: =0 -> 0 | F65: =0 -> 0 | G65: =0 -> 0 | H65: =0 -> 0 | I65: =0 -> 0 | J65: =0 -> 0 | K65: =0 -> 0 | L65: =0 -> 0 | M65: =IF(EXACT("API","Cyber-cafes"),'Model inputs'!C43*'Model inputs'!B12,IF(EXACT("API","API"),'Model inputs'!B46/12,'Model inputs'!B6*MIN('Model inputs'!B14,'Model inputs'!B44))) -> 2500 | N65: =IF('Model inputs'!N51="","",'Model inputs'!N51) -> 2500 | O65: =IF('Model inputs'!O51="","",'Model inputs'!O51) -> 2500 | P65: =IF('Model inputs'!P51="","",'Model inputs'!P51) -> 2500 | Q65: =IF('Model inputs'!Q51="","",'Model inputs'!Q51) -> 2500 | R65: =IF('Model inputs'!R51="","",'Model inputs'!R51) -> 2500 | S65: =IF('Model inputs'!S51="","",'Model inputs'!S51) -> 2500 | T65: =IF('Model inputs'!T51="","",'Model inputs'!T51) -> 2500 | U65: =IF('Model inputs'!U51="","",'Model inputs'!U51) -> 2500 | ... Y65: =IF('Model inputs'!Y51="","",'Model inputs'!Y51) -> 2500 | Z65: =IF(EXACT("API","Cyber-cafes"),'Model inputs'!C43*'Model inputs'!B12,IF(EXACT("API","API"),'Model inputs'!B46/12,'Model inputs'!B6*MIN('Model inputs'!B14,'Model inputs'!B44))) -> 2500 | AA65: =IF(EXACT("API","Cyber-cafes"),'Model inputs'!C43*'Model inputs'!B12,IF(EXACT("API","API"),'Model inputs'!B46/12,'Model inputs'!B6*MIN('Model inputs'!B14,'Model inputs'!B44))) -> 2500
A66: NS checks > Cyber-cafes | D66: =0 -> 0 | E66: =0 -> 0 | F66: =0 -> 0 | G66: =0 -> 0 | H66: =0 -> 0 | I66: =0 -> 0 | J66: =0 -> 0 | K66: =0 -> 0 | L66: =0 -> 0 | M66: =IF(EXACT("Cyber-cafes","Cyber-cafes"),'Model inputs'!C43*'Model inputs'!B12,IF(EXACT("Cyber-cafes","API"),'Model inputs'!B46/12,'Model inputs'!B6*MIN('Model inputs'!B14,'Model inputs'!B44))) -> 2000 | N66: =IF('Model inputs'!N52="","",'Model inputs'!N52) -> 2000 | O66: =IF('Model inputs'!O52="","",'Model inputs'!O52) -> 2000 | P66: =IF('Model inputs'!P52="","",'Model inputs'!P52) -> 2000 | Q66: =IF('Model inputs'!Q52="","",'Model inputs'!Q52) -> 2000 | R66: =IF('Model inputs'!R52="","",'Model inputs'!R52) -> 2000 | S66: =IF('Model inputs'!S52="","",'Model inputs'!S52) -> 2000 | T66: =IF('Model inputs'!T52="","",'Model inputs'!T52) -> 2000 | U66: =IF('Model inputs'!U52="","",'Model inputs'!U52) -> 2000 | ... Y66: =IF('Model inputs'!Y52="","",'Model inputs'!Y52) -> 2000 | Z66: =IF(EXACT("Cyber-cafes","Cyber-cafes"),'Model inputs'!C43*'Model inputs'!B12,IF(EXACT("Cyber-cafes","API"),'Model inputs'!B46/12,'Model inputs'!B6*MIN('Model inputs'!B14,'Model inputs'!B44))) -> 2000 | AA66: =IF(EXACT("Cyber-cafes","Cyber-cafes"),'Model inputs'!C43*'Model inputs'!B12,IF(EXACT("Cyber-cafes","API"),'Model inputs'!B46/12,'Model inputs'!B6*MIN('Model inputs'!B14,'Model inputs'!B44))) -> 2000
A67: NS checks > Students | D67: =0 -> 0 | E67: =0 -> 0 | F67: =0 -> 0 | G67: =0 -> 0 | H67: =0 -> 0 | I67: =0 -> 0 | J67: =0 -> 0 | K67: =0 -> 0 | L67: =0 -> 0 | M67: =IF(EXACT("Students","Cyber-cafes"),'Model inputs'!C43*'Model inputs'!B12,IF(EXACT("Students","API"),'Model inputs'!B46/12,'Model inputs'!B6*MIN('Model inputs'!B14,'Model inputs'!B44))) -> 3000 | N67: =IF('Model inputs'!N53="","",'Model inputs'!N53) -> 3000 | O67: =IF('Model inputs'!O53="","",'Model inputs'!O53) -> 3000 | P67: =IF('Model inputs'!P53="","",'Model inputs'!P53) -> 3000 | Q67: =IF('Model inputs'!Q53="","",'Model inputs'!Q53) -> 3000 | R67: =IF('Model inputs'!R53="","",'Model inputs'!R53) -> 3000 | S67: =IF('Model inputs'!S53="","",'Model inputs'!S53) -> 3000 | T67: =IF('Model inputs'!T53="","",'Model inputs'!T53) -> 3000 | U67: =IF('Model inputs'!U53="","",'Model inputs'!U53) -> 3000 | ... Y67: =IF('Model inputs'!Y53="","",'Model inputs'!Y53) -> 3000 | Z67: =IF(EXACT("Students","Cyber-cafes"),'Model inputs'!C43*'Model inputs'!B12,IF(EXACT("Students","API"),'Model inputs'!B46/12,'Model inputs'!B6*MIN('Model inputs'!B14,'Model inputs'!B44))) -> 3000 | AA67: =IF(EXACT("Students","Cyber-cafes"),'Model inputs'!C43*'Model inputs'!B12,IF(EXACT("Students","API"),'Model inputs'!B46/12,'Model inputs'!B6*MIN('Model inputs'!B14,'Model inputs'!B44))) -> 3000
A68: NS gross profit · NS operating profit · Year 1 totals and 45-cafe break-even · Main Scenario · Main Scenario | D68: 0 | E68: 0 | F68: 0 | G68: 0 | H68: 0 | I68: 0 | J68: 0 | K68: =IF('Model inputs'!K54="","",'Model inputs'!K54) -> 0 | L68: =IF('Model inputs'!L54="","",'Model inputs'!L54) -> 0 | M68: =IF('Model inputs'!M54="","",'Model inputs'!M54) -> 205425 | N68: =IF('Model inputs'!N54="","",'Model inputs'!N54) -> 205425 | O68: =IF('Model inputs'!O54="","",'Model inputs'!O54) -> 205425 | P68: =IF('Model inputs'!P54="","",'Model inputs'!P54) -> 205425 | Q68: =IF('Model inputs'!Q54="","",'Model inputs'!Q54) -> 205425 | R68: =IF('Model inputs'!R54="","",'Model inputs'!R54) -> 205425 | ... Y68: =IF('Model inputs'!Y54="","",'Model inputs'!Y54) -> 205425 | Z68: ='Model inputs'!Z32-'Model inputs'!Z20 -> 205425 | AA68: ='Model inputs'!AA32-'Model inputs'!AA20 -> 205425
A69: NS gross profit · NS operating profit · NaukriShield — Upside · NaukriShield — Upside | D69: 0 | E69: 0 | F69: 0 | G69: 0 | H69: 0 | I69: 0 | J69: 0 | K69: 0 | L69: 0 | M69: ='Model inputs'!M37-'Model inputs'!M25 -> 356450 | N69: ='Model inputs'!N37-'Model inputs'!N25 -> 356450 | O69: ='Model inputs'!O37-'Model inputs'!O25 -> 356450 | P69: ='Model inputs'!P37-'Model inputs'!P25 -> 356450 | Q69: ='Model inputs'!Q37-'Model inputs'!Q25 -> 356450 | R69: ='Model inputs'!R37-'Model inputs'!R25 -> 356450 | S69: ='Model inputs'!S37-'Model inputs'!S25 -> 356450 | T69: ='Model inputs'!T37-'Model inputs'!T25 -> 356450 | ... AA69: ='Model inputs'!AA37-'Model inputs'!AA25 -> 356450
A70: NS gross profit · NS operating profit · NaukriShield — Downside · NaukriShield — Downside | D70: 0 | E70: 0 | F70: 0 | G70: 0 | H70: 0 | I70: 0 | J70: 0 | K70: 0 | L70: 0 | M70: ='Model inputs'!M38-'Model inputs'!M26 -> 2780 | N70: ='Model inputs'!N38-'Model inputs'!N26 -> 2780 | O70: ='Model inputs'!O38-'Model inputs'!O26 -> 2780 | P70: ='Model inputs'!P38-'Model inputs'!P26 -> 2780 | Q70: ='Model inputs'!Q38-'Model inputs'!Q26 -> 2780 | R70: ='Model inputs'!R38-'Model inputs'!R26 -> 2780 | S70: ='Model inputs'!S38-'Model inputs'!S26 -> 2780 | T70: ='Model inputs'!T38-'Model inputs'!T26 -> 2780 | ... AA70: ='Model inputs'!AA38-'Model inputs'!AA26 -> 2780
A71: NS overhead · NS operating profit · Year 1 totals and 45-cafe break-even · Main Scenario · Main Scenario | D71: 0 | E71: 0 | F71: 0 | G71: 0 | H71: 0 | I71: 0 | J71: 0 | K71: =IF('Model inputs'!K55="","",'Model inputs'!K55) -> 0 | L71: =IF('Model inputs'!L55="","",'Model inputs'!L55) -> 0 | M71: =IF('Model inputs'!M55="","",'Model inputs'!M55) -> 14692.5 | N71: =IF('Model inputs'!N55="","",'Model inputs'!N55) -> 14692.5 | O71: =IF('Model inputs'!O55="","",'Model inputs'!O55) -> 14692.5 | P71: =IF('Model inputs'!P55="","",'Model inputs'!P55) -> 14692.5 | Q71: =IF('Model inputs'!Q55="","",'Model inputs'!Q55) -> 14692.5 | R71: =IF('Model inputs'!R55="","",'Model inputs'!R55) -> 14692.5 | ... Y71: =IF('Model inputs'!Y55="","",'Model inputs'!Y55) -> 14692.5 | Z71: =IF('Model inputs'!B18="","",'Model inputs'!B18) -> 14692.5 | AA71: =IF('Model inputs'!B18="","",'Model inputs'!B18) -> 14692.5
A72: NS overhead · NS operating profit · NaukriShield — Upside · NaukriShield — Upside | D72: 0 | E72: 0 | F72: 0 | G72: 0 | H72: 0 | I72: 0 | J72: 0 | K72: 0 | L72: 0 | M72: =IF('Model inputs'!C90="","",'Model inputs'!C90) -> 14692.5 | N72: =IF('Model inputs'!C90="","",'Model inputs'!C90) -> 14692.5 | O72: =IF('Model inputs'!C90="","",'Model inputs'!C90) -> 14692.5 | P72: =IF('Model inputs'!C90="","",'Model inputs'!C90) -> 14692.5 | Q72: =IF('Model inputs'!C90="","",'Model inputs'!C90) -> 14692.5 | R72: =IF('Model inputs'!C90="","",'Model inputs'!C90) -> 14692.5 | S72: =IF('Model inputs'!C90="","",'Model inputs'!C90) -> 14692.5 | T72: =IF('Model inputs'!C90="","",'Model inputs'!C90) -> 14692.5 | U72: =IF('Model inputs'!C90="","",'Model inputs'!C90) -> 14692.5 | V72: =IF('Model inputs'!C90="","",'Model inputs'!C90) -> 14692.5 | W72: =IF('Model inputs'!C90="","",'Model inputs'!C90) -> 14692.5 | X72: =IF('Model inputs'!C90="","",'Model inputs'!C90) -> 14692.5 | Y72: =IF('Model inputs'!C90="","",'Model inputs'!C90) -> 14692.5 | Z72: =IF('Model inputs'!C90="","",'Model inputs'!C90) -> 14692.5 | AA72: =IF('Model inputs'!C90="","",'Model inputs'!C90) -> 14692.5
A73: NS overhead · NS operating profit · NaukriShield — Downside · NaukriShield — Downside | D73: 0 | E73: 0 | F73: 0 | G73: 0 | H73: 0 | I73: 0 | J73: 0 | K73: 0 | L73: 0 | M73: =IF('Model inputs'!C91="","",'Model inputs'!C91) -> 14692.5 | N73: =IF('Model inputs'!C91="","",'Model inputs'!C91) -> 14692.5 | O73: =IF('Model inputs'!C91="","",'Model inputs'!C91) -> 14692.5 | P73: =IF('Model inputs'!C91="","",'Model inputs'!C91) -> 14692.5 | Q73: =IF('Model inputs'!C91="","",'Model inputs'!C91) -> 14692.5 | R73: =IF('Model inputs'!C91="","",'Model inputs'!C91) -> 14692.5 | S73: =IF('Model inputs'!C91="","",'Model inputs'!C91) -> 14692.5 | T73: =IF('Model inputs'!C91="","",'Model inputs'!C91) -> 14692.5 | U73: =IF('Model inputs'!C91="","",'Model inputs'!C91) -> 14692.5 | V73: =IF('Model inputs'!C91="","",'Model inputs'!C91) -> 14692.5 | W73: =IF('Model inputs'!C91="","",'Model inputs'!C91) -> 14692.5 | X73: =IF('Model inputs'!C91="","",'Model inputs'!C91) -> 14692.5 | Y73: =IF('Model inputs'!C91="","",'Model inputs'!C91) -> 14692.5 | Z73: =IF('Model inputs'!C91="","",'Model inputs'!C91) -> 14692.5 | AA73: =IF('Model inputs'!C91="","",'Model inputs'!C91) -> 14692.5
A74: NS revenue | D74: =IF('Model inputs'!D37="","",'Model inputs'!D37) -> 0 | E74: =IF('Model inputs'!E37="","",'Model inputs'!E37) -> 0 | F74: =IF('Model inputs'!F37="","",'Model inputs'!F37) -> 0 | G74: =IF('Model inputs'!G37="","",'Model inputs'!G37) -> 0 | H74: =IF('Model inputs'!H37="","",'Model inputs'!H37) -> 0 | I74: =IF('Model inputs'!I37="","",'Model inputs'!I37) -> 0 | J74: =IF('Model inputs'!J37="","",'Model inputs'!J37) -> 0 | K74: =IF('Model inputs'!K37="","",'Model inputs'!K37) -> 0 | ... AA74: =IF('Model inputs'!AA37="","",'Model inputs'!AA37) -> 394700
A75: NS revenue > API | D75: ='Model inputs'!D34 -> 0 | E75: ='Model inputs'!E34 -> 0 | F75: ='Model inputs'!F34 -> 0 | G75: ='Model inputs'!G34 -> 0 | H75: ='Model inputs'!H34 -> 0 | I75: ='Model inputs'!I34 -> 0 | J75: ='Model inputs'!J34 -> 0 | K75: ='Model inputs'!K34 -> 0 | L75: ='Model inputs'!L34 -> 0 | M75: =IF(EXACT("API","Cyber-cafes"),'Model inputs'!C100*'Model inputs'!C86,IF(EXACT("API","API"),'Model inputs'!C102/12*'Model inputs'!C84,0)) -> 245000 | N75: =IF(EXACT("API","Cyber-cafes"),'Model inputs'!C100*'Model inputs'!C86,IF(EXACT("API","API"),'Model inputs'!C102/12*'Model inputs'!C84,0)) -> 245000 | O75: =IF(EXACT("API","Cyber-cafes"),'Model inputs'!C100*'Model inputs'!C86,IF(EXACT("API","API"),'Model inputs'!C102/12*'Model inputs'!C84,0)) -> 245000 | P75: =IF(EXACT("API","Cyber-cafes"),'Model inputs'!C100*'Model inputs'!C86,IF(EXACT("API","API"),'Model inputs'!C102/12*'Model inputs'!C84,0)) -> 245000 | Q75: =IF(EXACT("API","Cyber-cafes"),'Model inputs'!C100*'Model inputs'!C86,IF(EXACT("API","API"),'Model inputs'!C102/12*'Model inputs'!C84,0)) -> 245000 | R75: =IF(EXACT("API","Cyber-cafes"),'Model inputs'!C100*'Model inputs'!C86,IF(EXACT("API","API"),'Model inputs'!C102/12*'Model inputs'!C84,0)) -> 245000 | S75: =IF(EXACT("API","Cyber-cafes"),'Model inputs'!C100*'Model inputs'!C86,IF(EXACT("API","API"),'Model inputs'!C102/12*'Model inputs'!C84,0)) -> 245000 | T75: =IF(EXACT("API","Cyber-cafes"),'Model inputs'!C100*'Model inputs'!C86,IF(EXACT("API","API"),'Model inputs'!C102/12*'Model inputs'!C84,0)) -> 245000 | U75: =IF(EXACT("API","Cyber-cafes"),'Model inputs'!C100*'Model inputs'!C86,IF(EXACT("API","API"),'Model inputs'!C102/12*'Model inputs'!C84,0)) -> 245000 | V75: =IF(EXACT("API","Cyber-cafes"),'Model inputs'!C100*'Model inputs'!C86,IF(EXACT("API","API"),'Model inputs'!C102/12*'Model inputs'!C84,0)) -> 245000 | W75: =IF(EXACT("API","Cyber-cafes"),'Model inputs'!C100*'Model inputs'!C86,IF(EXACT("API","API"),'Model inputs'!C102/12*'Model inputs'!C84,0)) -> 245000 | X75: =IF(EXACT("API","Cyber-cafes"),'Model inputs'!C100*'Model inputs'!C86,IF(EXACT("API","API"),'Model inputs'!C102/12*'Model inputs'!C84,0)) -> 245000 | Y75: =IF(EXACT("API","Cyber-cafes"),'Model inputs'!C100*'Model inputs'!C86,IF(EXACT("API","API"),'Model inputs'!C102/12*'Model inputs'!C84,0)) -> 245000 | Z75: =IF(EXACT("API","Cyber-cafes"),'Model inputs'!C100*'Model inputs'!C86,IF(EXACT("API","API"),'Model inputs'!C102/12*'Model inputs'!C84,0)) -> 245000 | AA75: =IF(EXACT("API","Cyber-cafes"),'Model inputs'!C100*'Model inputs'!C86,IF(EXACT("API","API"),'Model inputs'!C102/12*'Model inputs'!C84,0)) -> 245000
A76: NS revenue > Cyber-cafes | D76: ='Model inputs'!D35 -> 0 | E76: ='Model inputs'!E35 -> 0 | F76: ='Model inputs'!F35 -> 0 | G76: ='Model inputs'!G35 -> 0 | H76: ='Model inputs'!H35 -> 0 | I76: ='Model inputs'!I35 -> 0 | J76: ='Model inputs'!J35 -> 0 | K76: ='Model inputs'!K35 -> 0 | L76: ='Model inputs'!L35 -> 0 | M76: =IF(EXACT("Cyber-cafes","Cyber-cafes"),'Model inputs'!C100*'Model inputs'!C86,IF(EXACT("Cyber-cafes","API"),'Model inputs'!C102/12*'Model inputs'!C84,0)) -> 149700 | N76: =IF(EXACT("Cyber-cafes","Cyber-cafes"),'Model inputs'!C100*'Model inputs'!C86,IF(EXACT("Cyber-cafes","API"),'Model inputs'!C102/12*'Model inputs'!C84,0)) -> 149700 | O76: =IF(EXACT("Cyber-cafes","Cyber-cafes"),'Model inputs'!C100*'Model inputs'!C86,IF(EXACT("Cyber-cafes","API"),'Model inputs'!C102/12*'Model inputs'!C84,0)) -> 149700 | P76: =IF(EXACT("Cyber-cafes","Cyber-cafes"),'Model inputs'!C100*'Model inputs'!C86,IF(EXACT("Cyber-cafes","API"),'Model inputs'!C102/12*'Model inputs'!C84,0)) -> 149700 | Q76: =IF(EXACT("Cyber-cafes","Cyber-cafes"),'Model inputs'!C100*'Model inputs'!C86,IF(EXACT("Cyber-cafes","API"),'Model inputs'!C102/12*'Model inputs'!C84,0)) -> 149700 | R76: =IF(EXACT("Cyber-cafes","Cyber-cafes"),'Model inputs'!C100*'Model inputs'!C86,IF(EXACT("Cyber-cafes","API"),'Model inputs'!C102/12*'Model inputs'!C84,0)) -> 149700 | S76: =IF(EXACT("Cyber-cafes","Cyber-cafes"),'Model inputs'!C100*'Model inputs'!C86,IF(EXACT("Cyber-cafes","API"),'Model inputs'!C102/12*'Model inputs'!C84,0)) -> 149700 | T76: =IF(EXACT("Cyber-cafes","Cyber-cafes"),'Model inputs'!C100*'Model inputs'!C86,IF(EXACT("Cyber-cafes","API"),'Model inputs'!C102/12*'Model inputs'!C84,0)) -> 149700 | U76: =IF(EXACT("Cyber-cafes","Cyber-cafes"),'Model inputs'!C100*'Model inputs'!C86,IF(EXACT("Cyber-cafes","API"),'Model inputs'!C102/12*'Model inputs'!C84,0)) -> 149700 | V76: =IF(EXACT("Cyber-cafes","Cyber-cafes"),'Model inputs'!C100*'Model inputs'!C86,IF(EXACT("Cyber-cafes","API"),'Model inputs'!C102/12*'Model inputs'!C84,0)) -> 149700 | W76: =IF(EXACT("Cyber-cafes","Cyber-cafes"),'Model inputs'!C100*'Model inputs'!C86,IF(EXACT("Cyber-cafes","API"),'Model inputs'!C102/12*'Model inputs'!C84,0)) -> 149700 | X76: =IF(EXACT("Cyber-cafes","Cyber-cafes"),'Model inputs'!C100*'Model inputs'!C86,IF(EXACT("Cyber-cafes","API"),'Model inputs'!C102/12*'Model inputs'!C84,0)) -> 149700 | Y76: =IF(EXACT("Cyber-cafes","Cyber-cafes"),'Model inputs'!C100*'Model inputs'!C86,IF(EXACT("Cyber-cafes","API"),'Model inputs'!C102/12*'Model inputs'!C84,0)) -> 149700 | Z76: =IF(EXACT("Cyber-cafes","Cyber-cafes"),'Model inputs'!C100*'Model inputs'!C86,IF(EXACT("Cyber-cafes","API"),'Model inputs'!C102/12*'Model inputs'!C84,0)) -> 149700 | AA76: =IF(EXACT("Cyber-cafes","Cyber-cafes"),'Model inputs'!C100*'Model inputs'!C86,IF(EXACT("Cyber-cafes","API"),'Model inputs'!C102/12*'Model inputs'!C84,0)) -> 149700
A77: NS revenue > Students | D77: ='Model inputs'!D36 -> 0 | E77: ='Model inputs'!E36 -> 0 | F77: ='Model inputs'!F36 -> 0 | G77: ='Model inputs'!G36 -> 0 | H77: ='Model inputs'!H36 -> 0 | I77: ='Model inputs'!I36 -> 0 | J77: ='Model inputs'!J36 -> 0 | K77: ='Model inputs'!K36 -> 0 | L77: ='Model inputs'!L36 -> 0 | M77: =IF(EXACT("Students","Cyber-cafes"),'Model inputs'!C100*'Model inputs'!C86,IF(EXACT("Students","API"),'Model inputs'!C102/12*'Model inputs'!C84,0)) -> 0 | N77: =IF(EXACT("Students","Cyber-cafes"),'Model inputs'!C100*'Model inputs'!C86,IF(EXACT("Students","API"),'Model inputs'!C102/12*'Model inputs'!C84,0)) -> 0 | O77: =IF(EXACT("Students","Cyber-cafes"),'Model inputs'!C100*'Model inputs'!C86,IF(EXACT("Students","API"),'Model inputs'!C102/12*'Model inputs'!C84,0)) -> 0 | P77: =IF(EXACT("Students","Cyber-cafes"),'Model inputs'!C100*'Model inputs'!C86,IF(EXACT("Students","API"),'Model inputs'!C102/12*'Model inputs'!C84,0)) -> 0 | Q77: =IF(EXACT("Students","Cyber-cafes"),'Model inputs'!C100*'Model inputs'!C86,IF(EXACT("Students","API"),'Model inputs'!C102/12*'Model inputs'!C84,0)) -> 0 | R77: =IF(EXACT("Students","Cyber-cafes"),'Model inputs'!C100*'Model inputs'!C86,IF(EXACT("Students","API"),'Model inputs'!C102/12*'Model inputs'!C84,0)) -> 0 | S77: =IF(EXACT("Students","Cyber-cafes"),'Model inputs'!C100*'Model inputs'!C86,IF(EXACT("Students","API"),'Model inputs'!C102/12*'Model inputs'!C84,0)) -> 0 | T77: =IF(EXACT("Students","Cyber-cafes"),'Model inputs'!C100*'Model inputs'!C86,IF(EXACT("Students","API"),'Model inputs'!C102/12*'Model inputs'!C84,0)) -> 0 | U77: =IF(EXACT("Students","Cyber-cafes"),'Model inputs'!C100*'Model inputs'!C86,IF(EXACT("Students","API"),'Model inputs'!C102/12*'Model inputs'!C84,0)) -> 0 | V77: =IF(EXACT("Students","Cyber-cafes"),'Model inputs'!C100*'Model inputs'!C86,IF(EXACT("Students","API"),'Model inputs'!C102/12*'Model inputs'!C84,0)) -> 0 | W77: =IF(EXACT("Students","Cyber-cafes"),'Model inputs'!C100*'Model inputs'!C86,IF(EXACT("Students","API"),'Model inputs'!C102/12*'Model inputs'!C84,0)) -> 0 | X77: =IF(EXACT("Students","Cyber-cafes"),'Model inputs'!C100*'Model inputs'!C86,IF(EXACT("Students","API"),'Model inputs'!C102/12*'Model inputs'!C84,0)) -> 0 | Y77: =IF(EXACT("Students","Cyber-cafes"),'Model inputs'!C100*'Model inputs'!C86,IF(EXACT("Students","API"),'Model inputs'!C102/12*'Model inputs'!C84,0)) -> 0 | Z77: =IF(EXACT("Students","Cyber-cafes"),'Model inputs'!C100*'Model inputs'!C86,IF(EXACT("Students","API"),'Model inputs'!C102/12*'Model inputs'!C84,0)) -> 0 | AA77: =IF(EXACT("Students","Cyber-cafes"),'Model inputs'!C100*'Model inputs'!C86,IF(EXACT("Students","API"),'Model inputs'!C102/12*'Model inputs'!C84,0)) -> 0
A78: NS revenue | D78: =IF('Model inputs'!D38="","",'Model inputs'!D38) -> 0 | E78: =IF('Model inputs'!E38="","",'Model inputs'!E38) -> 0 | F78: =IF('Model inputs'!F38="","",'Model inputs'!F38) -> 0 | G78: =IF('Model inputs'!G38="","",'Model inputs'!G38) -> 0 | H78: =IF('Model inputs'!H38="","",'Model inputs'!H38) -> 0 | I78: =IF('Model inputs'!I38="","",'Model inputs'!I38) -> 0 | J78: =IF('Model inputs'!J38="","",'Model inputs'!J38) -> 0 | K78: =IF('Model inputs'!K38="","",'Model inputs'!K38) -> 0 | ... AA78: =IF('Model inputs'!AA38="","",'Model inputs'!AA38) -> 9980
A79: NS revenue > API | D79: ='Model inputs'!D34 -> 0 | E79: ='Model inputs'!E34 -> 0 | F79: ='Model inputs'!F34 -> 0 | G79: ='Model inputs'!G34 -> 0 | H79: ='Model inputs'!H34 -> 0 | I79: ='Model inputs'!I34 -> 0 | J79: ='Model inputs'!J34 -> 0 | K79: ='Model inputs'!K34 -> 0 | L79: ='Model inputs'!L34 -> 0 | M79: =IF(EXACT("API","Cyber-cafes"),'Model inputs'!C101*'Model inputs'!C87,IF(EXACT("API","API"),'Model inputs'!C103/12*'Model inputs'!C85,0)) -> 0 | N79: =IF(EXACT("API","Cyber-cafes"),'Model inputs'!C101*'Model inputs'!C87,IF(EXACT("API","API"),'Model inputs'!C103/12*'Model inputs'!C85,0)) -> 0 | O79: =IF(EXACT("API","Cyber-cafes"),'Model inputs'!C101*'Model inputs'!C87,IF(EXACT("API","API"),'Model inputs'!C103/12*'Model inputs'!C85,0)) -> 0 | P79: =IF(EXACT("API","Cyber-cafes"),'Model inputs'!C101*'Model inputs'!C87,IF(EXACT("API","API"),'Model inputs'!C103/12*'Model inputs'!C85,0)) -> 0 | Q79: =IF(EXACT("API","Cyber-cafes"),'Model inputs'!C101*'Model inputs'!C87,IF(EXACT("API","API"),'Model inputs'!C103/12*'Model inputs'!C85,0)) -> 0 | R79: =IF(EXACT("API","Cyber-cafes"),'Model inputs'!C101*'Model inputs'!C87,IF(EXACT("API","API"),'Model inputs'!C103/12*'Model inputs'!C85,0)) -> 0 | S79: =IF(EXACT("API","Cyber-cafes"),'Model inputs'!C101*'Model inputs'!C87,IF(EXACT("API","API"),'Model inputs'!C103/12*'Model inputs'!C85,0)) -> 0 | T79: =IF(EXACT("API","Cyber-cafes"),'Model inputs'!C101*'Model inputs'!C87,IF(EXACT("API","API"),'Model inputs'!C103/12*'Model inputs'!C85,0)) -> 0 | U79: =IF(EXACT("API","Cyber-cafes"),'Model inputs'!C101*'Model inputs'!C87,IF(EXACT("API","API"),'Model inputs'!C103/12*'Model inputs'!C85,0)) -> 0 | V79: =IF(EXACT("API","Cyber-cafes"),'Model inputs'!C101*'Model inputs'!C87,IF(EXACT("API","API"),'Model inputs'!C103/12*'Model inputs'!C85,0)) -> 0 | W79: =IF(EXACT("API","Cyber-cafes"),'Model inputs'!C101*'Model inputs'!C87,IF(EXACT("API","API"),'Model inputs'!C103/12*'Model inputs'!C85,0)) -> 0 | X79: =IF(EXACT("API","Cyber-cafes"),'Model inputs'!C101*'Model inputs'!C87,IF(EXACT("API","API"),'Model inputs'!C103/12*'Model inputs'!C85,0)) -> 0 | Y79: =IF(EXACT("API","Cyber-cafes"),'Model inputs'!C101*'Model inputs'!C87,IF(EXACT("API","API"),'Model inputs'!C103/12*'Model inputs'!C85,0)) -> 0 | Z79: =IF(EXACT("API","Cyber-cafes"),'Model inputs'!C101*'Model inputs'!C87,IF(EXACT("API","API"),'Model inputs'!C103/12*'Model inputs'!C85,0)) -> 0 | AA79: =IF(EXACT("API","Cyber-cafes"),'Model inputs'!C101*'Model inputs'!C87,IF(EXACT("API","API"),'Model inputs'!C103/12*'Model inputs'!C85,0)) -> 0
A80: NS revenue > Cyber-cafes | D80: ='Model inputs'!D35 -> 0 | E80: ='Model inputs'!E35 -> 0 | F80: ='Model inputs'!F35 -> 0 | G80: ='Model inputs'!G35 -> 0 | H80: ='Model inputs'!H35 -> 0 | I80: ='Model inputs'!I35 -> 0 | J80: ='Model inputs'!J35 -> 0 | K80: ='Model inputs'!K35 -> 0 | L80: ='Model inputs'!L35 -> 0 | M80: =IF(EXACT("Cyber-cafes","Cyber-cafes"),'Model inputs'!C101*'Model inputs'!C87,IF(EXACT("Cyber-cafes","API"),'Model inputs'!C103/12*'Model inputs'!C85,0)) -> 9980 | N80: =IF(EXACT("Cyber-cafes","Cyber-cafes"),'Model inputs'!C101*'Model inputs'!C87,IF(EXACT("Cyber-cafes","API"),'Model inputs'!C103/12*'Model inputs'!C85,0)) -> 9980 | O80: =IF(EXACT("Cyber-cafes","Cyber-cafes"),'Model inputs'!C101*'Model inputs'!C87,IF(EXACT("Cyber-cafes","API"),'Model inputs'!C103/12*'Model inputs'!C85,0)) -> 9980 | P80: =IF(EXACT("Cyber-cafes","Cyber-cafes"),'Model inputs'!C101*'Model inputs'!C87,IF(EXACT("Cyber-cafes","API"),'Model inputs'!C103/12*'Model inputs'!C85,0)) -> 9980 | Q80: =IF(EXACT("Cyber-cafes","Cyber-cafes"),'Model inputs'!C101*'Model inputs'!C87,IF(EXACT("Cyber-cafes","API"),'Model inputs'!C103/12*'Model inputs'!C85,0)) -> 9980 | R80: =IF(EXACT("Cyber-cafes","Cyber-cafes"),'Model inputs'!C101*'Model inputs'!C87,IF(EXACT("Cyber-cafes","API"),'Model inputs'!C103/12*'Model inputs'!C85,0)) -> 9980 | S80: =IF(EXACT("Cyber-cafes","Cyber-cafes"),'Model inputs'!C101*'Model inputs'!C87,IF(EXACT("Cyber-cafes","API"),'Model inputs'!C103/12*'Model inputs'!C85,0)) -> 9980 | T80: =IF(EXACT("Cyber-cafes","Cyber-cafes"),'Model inputs'!C101*'Model inputs'!C87,IF(EXACT("Cyber-cafes","API"),'Model inputs'!C103/12*'Model inputs'!C85,0)) -> 9980 | U80: =IF(EXACT("Cyber-cafes","Cyber-cafes"),'Model inputs'!C101*'Model inputs'!C87,IF(EXACT("Cyber-cafes","API"),'Model inputs'!C103/12*'Model inputs'!C85,0)) -> 9980 | V80: =IF(EXACT("Cyber-cafes","Cyber-cafes"),'Model inputs'!C101*'Model inputs'!C87,IF(EXACT("Cyber-cafes","API"),'Model inputs'!C103/12*'Model inputs'!C85,0)) -> 9980 | W80: =IF(EXACT("Cyber-cafes","Cyber-cafes"),'Model inputs'!C101*'Model inputs'!C87,IF(EXACT("Cyber-cafes","API"),'Model inputs'!C103/12*'Model inputs'!C85,0)) -> 9980 | X80: =IF(EXACT("Cyber-cafes","Cyber-cafes"),'Model inputs'!C101*'Model inputs'!C87,IF(EXACT("Cyber-cafes","API"),'Model inputs'!C103/12*'Model inputs'!C85,0)) -> 9980 | Y80: =IF(EXACT("Cyber-cafes","Cyber-cafes"),'Model inputs'!C101*'Model inputs'!C87,IF(EXACT("Cyber-cafes","API"),'Model inputs'!C103/12*'Model inputs'!C85,0)) -> 9980 | Z80: =IF(EXACT("Cyber-cafes","Cyber-cafes"),'Model inputs'!C101*'Model inputs'!C87,IF(EXACT("Cyber-cafes","API"),'Model inputs'!C103/12*'Model inputs'!C85,0)) -> 9980 | AA80: =IF(EXACT("Cyber-cafes","Cyber-cafes"),'Model inputs'!C101*'Model inputs'!C87,IF(EXACT("Cyber-cafes","API"),'Model inputs'!C103/12*'Model inputs'!C85,0)) -> 9980
A81: NS revenue > Students | D81: ='Model inputs'!D36 -> 0 | E81: ='Model inputs'!E36 -> 0 | F81: ='Model inputs'!F36 -> 0 | G81: ='Model inputs'!G36 -> 0 | H81: ='Model inputs'!H36 -> 0 | I81: ='Model inputs'!I36 -> 0 | J81: ='Model inputs'!J36 -> 0 | K81: ='Model inputs'!K36 -> 0 | L81: ='Model inputs'!L36 -> 0 | M81: =IF(EXACT("Students","Cyber-cafes"),'Model inputs'!C101*'Model inputs'!C87,IF(EXACT("Students","API"),'Model inputs'!C103/12*'Model inputs'!C85,0)) -> 0 | N81: =IF(EXACT("Students","Cyber-cafes"),'Model inputs'!C101*'Model inputs'!C87,IF(EXACT("Students","API"),'Model inputs'!C103/12*'Model inputs'!C85,0)) -> 0 | O81: =IF(EXACT("Students","Cyber-cafes"),'Model inputs'!C101*'Model inputs'!C87,IF(EXACT("Students","API"),'Model inputs'!C103/12*'Model inputs'!C85,0)) -> 0 | P81: =IF(EXACT("Students","Cyber-cafes"),'Model inputs'!C101*'Model inputs'!C87,IF(EXACT("Students","API"),'Model inputs'!C103/12*'Model inputs'!C85,0)) -> 0 | Q81: =IF(EXACT("Students","Cyber-cafes"),'Model inputs'!C101*'Model inputs'!C87,IF(EXACT("Students","API"),'Model inputs'!C103/12*'Model inputs'!C85,0)) -> 0 | R81: =IF(EXACT("Students","Cyber-cafes"),'Model inputs'!C101*'Model inputs'!C87,IF(EXACT("Students","API"),'Model inputs'!C103/12*'Model inputs'!C85,0)) -> 0 | S81: =IF(EXACT("Students","Cyber-cafes"),'Model inputs'!C101*'Model inputs'!C87,IF(EXACT("Students","API"),'Model inputs'!C103/12*'Model inputs'!C85,0)) -> 0 | T81: =IF(EXACT("Students","Cyber-cafes"),'Model inputs'!C101*'Model inputs'!C87,IF(EXACT("Students","API"),'Model inputs'!C103/12*'Model inputs'!C85,0)) -> 0 | U81: =IF(EXACT("Students","Cyber-cafes"),'Model inputs'!C101*'Model inputs'!C87,IF(EXACT("Students","API"),'Model inputs'!C103/12*'Model inputs'!C85,0)) -> 0 | V81: =IF(EXACT("Students","Cyber-cafes"),'Model inputs'!C101*'Model inputs'!C87,IF(EXACT("Students","API"),'Model inputs'!C103/12*'Model inputs'!C85,0)) -> 0 | W81: =IF(EXACT("Students","Cyber-cafes"),'Model inputs'!C101*'Model inputs'!C87,IF(EXACT("Students","API"),'Model inputs'!C103/12*'Model inputs'!C85,0)) -> 0 | X81: =IF(EXACT("Students","Cyber-cafes"),'Model inputs'!C101*'Model inputs'!C87,IF(EXACT("Students","API"),'Model inputs'!C103/12*'Model inputs'!C85,0)) -> 0 | Y81: =IF(EXACT("Students","Cyber-cafes"),'Model inputs'!C101*'Model inputs'!C87,IF(EXACT("Students","API"),'Model inputs'!C103/12*'Model inputs'!C85,0)) -> 0 | Z81: =IF(EXACT("Students","Cyber-cafes"),'Model inputs'!C101*'Model inputs'!C87,IF(EXACT("Students","API"),'Model inputs'!C103/12*'Model inputs'!C85,0)) -> 0 | AA81: =IF(EXACT("Students","Cyber-cafes"),'Model inputs'!C101*'Model inputs'!C87,IF(EXACT("Students","API"),'Model inputs'!C103/12*'Model inputs'!C85,0)) -> 0
A82: Cached data cost per check · Cost per check · Monthly revenue and check costs | C82: ='Pricing and editable planning i'!B9 -> 1.5
A83: Haiku cost per check · Cost per check · Monthly revenue and check costs | C83: ='Pricing and editable planning i'!B8 -> 0.75
A84: API check price · NS revenue · by NS customer channel · NaukriShield — Upside · NaukriShield — Upside | C84: ='Pricing and editable planning i'!B7 -> 49
A85: API check price · NS revenue · by NS customer channel · NaukriShield — Downside · NaukriShield — Downside | C85: ='Pricing and editable planning i'!B7 -> 49
A86: Cafe monthly price · NS revenue · by NS customer channel · NaukriShield — Upside · NaukriShield — Upside | C86: ='Pricing and editable planning i'!B6 -> 499
A87: Cafe monthly price · NS revenue · by NS customer channel · NaukriShield — Downside · NaukriShield — Downside | C87: ='Pricing and editable planning i'!B6 -> 499
A88: Cost per check · NS check costs · by NS customer channel · NaukriShield — Upside · NaukriShield — Upside | C88: ='Model inputs'!C112+'Model inputs'!C106 -> 2.25
A89: Cost per check · NS check costs · by NS customer channel · NaukriShield — Downside · NaukriShield — Downside | C89: ='Model inputs'!C113+'Model inputs'!C107 -> 2.25
A90: Monthly non-check overhead · NS overhead · NS operating profit · NaukriShield — Upside · NaukriShield — Upside · NaukriShield — Upside | C90: ='Pricing and editable planning i'!B16 -> 14692.5
A91: Monthly non-check overhead · NS overhead · NS operating profit · NaukriShield — Downside · NaukriShield — Downside · NaukriShield — Downside | C91: ='Pricing and editable planning i'!B16 -> 14692.5
A92: NS checks | D92: =SUM('Model inputs'!D93,'Model inputs'!D94,'Model inputs'!D95) -> 0 | E92: =SUM('Model inputs'!E93,'Model inputs'!E94,'Model inputs'!E95) -> 0 | F92: =SUM('Model inputs'!F93,'Model inputs'!F94,'Model inputs'!F95) -> 0 | G92: =SUM('Model inputs'!G93,'Model inputs'!G94,'Model inputs'!G95) -> 0 | H92: =SUM('Model inputs'!H93,'Model inputs'!H94,'Model inputs'!H95) -> 0 | I92: =SUM('Model inputs'!I93,'Model inputs'!I94,'Model inputs'!I95) -> 0 | J92: =SUM('Model inputs'!J93,'Model inputs'!J94,'Model inputs'!J95) -> 0 | K92: =SUM('Model inputs'!K93,'Model inputs'!K94,'Model inputs'!K95) -> 0 | ... AA92: =SUM('Model inputs'!AA93,'Model inputs'!AA94,'Model inputs'!AA95) -> 17000
A93: NS checks > API | D93: ='Model inputs'!D65 -> 0 | E93: ='Model inputs'!E65 -> 0 | F93: ='Model inputs'!F65 -> 0 | G93: ='Model inputs'!G65 -> 0 | H93: ='Model inputs'!H65 -> 0 | I93: ='Model inputs'!I65 -> 0 | J93: ='Model inputs'!J65 -> 0 | K93: ='Model inputs'!K65 -> 0 | L93: ='Model inputs'!L65 -> 0 | M93: =IF(EXACT("API","Cyber-cafes"),'Model inputs'!C100*'Model inputs'!C108,IF(EXACT("API","API"),'Model inputs'!C102/12,'Model inputs'!C104*MIN('Model inputs'!C110,'Model inputs'!C114))) -> 5000 | N93: =IF(EXACT("API","Cyber-cafes"),'Model inputs'!C100*'Model inputs'!C108,IF(EXACT("API","API"),'Model inputs'!C102/12,'Model inputs'!C104*MIN('Model inputs'!C110,'Model inputs'!C114))) -> 5000 | O93: =IF(EXACT("API","Cyber-cafes"),'Model inputs'!C100*'Model inputs'!C108,IF(EXACT("API","API"),'Model inputs'!C102/12,'Model inputs'!C104*MIN('Model inputs'!C110,'Model inputs'!C114))) -> 5000 | P93: =IF(EXACT("API","Cyber-cafes"),'Model inputs'!C100*'Model inputs'!C108,IF(EXACT("API","API"),'Model inputs'!C102/12,'Model inputs'!C104*MIN('Model inputs'!C110,'Model inputs'!C114))) -> 5000 | Q93: =IF(EXACT("API","Cyber-cafes"),'Model inputs'!C100*'Model inputs'!C108,IF(EXACT("API","API"),'Model inputs'!C102/12,'Model inputs'!C104*MIN('Model inputs'!C110,'Model inputs'!C114))) -> 5000 | R93: =IF(EXACT("API","Cyber-cafes"),'Model inputs'!C100*'Model inputs'!C108,IF(EXACT("API","API"),'Model inputs'!C102/12,'Model inputs'!C104*MIN('Model inputs'!C110,'Model inputs'!C114))) -> 5000 | S93: =IF(EXACT("API","Cyber-cafes"),'Model inputs'!C100*'Model inputs'!C108,IF(EXACT("API","API"),'Model inputs'!C102/12,'Model inputs'!C104*MIN('Model inputs'!C110,'Model inputs'!C114))) -> 5000 | T93: =IF(EXACT("API","Cyber-cafes"),'Model inputs'!C100*'Model inputs'!C108,IF(EXACT("API","API"),'Model inputs'!C102/12,'Model inputs'!C104*MIN('Model inputs'!C110,'Model inputs'!C114))) -> 5000 | U93: =IF(EXACT("API","Cyber-cafes"),'Model inputs'!C100*'Model inputs'!C108,IF(EXACT("API","API"),'Model inputs'!C102/12,'Model inputs'!C104*MIN('Model inputs'!C110,'Model inputs'!C114))) -> 5000 | V93: =IF(EXACT("API","Cyber-cafes"),'Model inputs'!C100*'Model inputs'!C108,IF(EXACT("API","API"),'Model inputs'!C102/12,'Model inputs'!C104*MIN('Model inputs'!C110,'Model inputs'!C114))) -> 5000 | W93: =IF(EXACT("API","Cyber-cafes"),'Model inputs'!C100*'Model inputs'!C108,IF(EXACT("API","API"),'Model inputs'!C102/12,'Model inputs'!C104*MIN('Model inputs'!C110,'Model inputs'!C114))) -> 5000 | X93: =IF(EXACT("API","Cyber-cafes"),'Model inputs'!C100*'Model inputs'!C108,IF(EXACT("API","API"),'Model inputs'!C102/12,'Model inputs'!C104*MIN('Model inputs'!C110,'Model inputs'!C114))) -> 5000 | Y93: =IF(EXACT("API","Cyber-cafes"),'Model inputs'!C100*'Model inputs'!C108,IF(EXACT("API","API"),'Model inputs'!C102/12,'Model inputs'!C104*MIN('Model inputs'!C110,'Model inputs'!C114))) -> 5000 | Z93: =IF(EXACT("API","Cyber-cafes"),'Model inputs'!C100*'Model inputs'!C108,IF(EXACT("API","API"),'Model inputs'!C102/12,'Model inputs'!C104*MIN('Model inputs'!C110,'Model inputs'!C114))) -> 5000 | AA93: =IF(EXACT("API","Cyber-cafes"),'Model inputs'!C100*'Model inputs'!C108,IF(EXACT("API","API"),'Model inputs'!C102/12,'Model inputs'!C104*MIN('Model inputs'!C110,'Model inputs'!C114))) -> 5000
A94: NS checks > Cyber-cafes | D94: ='Model inputs'!D66 -> 0 | E94: ='Model inputs'!E66 -> 0 | F94: ='Model inputs'!F66 -> 0 | G94: ='Model inputs'!G66 -> 0 | H94: ='Model inputs'!H66 -> 0 | I94: ='Model inputs'!I66 -> 0 | J94: ='Model inputs'!J66 -> 0 | K94: ='Model inputs'!K66 -> 0 | L94: ='Model inputs'!L66 -> 0 | M94: =IF(EXACT("Cyber-cafes","Cyber-cafes"),'Model inputs'!C100*'Model inputs'!C108,IF(EXACT("Cyber-cafes","API"),'Model inputs'!C102/12,'Model inputs'!C104*MIN('Model inputs'!C110,'Model inputs'!C114))) -> 6000 | N94: =IF(EXACT("Cyber-cafes","Cyber-cafes"),'Model inputs'!C100*'Model inputs'!C108,IF(EXACT("Cyber-cafes","API"),'Model inputs'!C102/12,'Model inputs'!C104*MIN('Model inputs'!C110,'Model inputs'!C114))) -> 6000 | O94: =IF(EXACT("Cyber-cafes","Cyber-cafes"),'Model inputs'!C100*'Model inputs'!C108,IF(EXACT("Cyber-cafes","API"),'Model inputs'!C102/12,'Model inputs'!C104*MIN('Model inputs'!C110,'Model inputs'!C114))) -> 6000 | P94: =IF(EXACT("Cyber-cafes","Cyber-cafes"),'Model inputs'!C100*'Model inputs'!C108,IF(EXACT("Cyber-cafes","API"),'Model inputs'!C102/12,'Model inputs'!C104*MIN('Model inputs'!C110,'Model inputs'!C114))) -> 6000 | Q94: =IF(EXACT("Cyber-cafes","Cyber-cafes"),'Model inputs'!C100*'Model inputs'!C108,IF(EXACT("Cyber-cafes","API"),'Model inputs'!C102/12,'Model inputs'!C104*MIN('Model inputs'!C110,'Model inputs'!C114))) -> 6000 | R94: =IF(EXACT("Cyber-cafes","Cyber-cafes"),'Model inputs'!C100*'Model inputs'!C108,IF(EXACT("Cyber-cafes","API"),'Model inputs'!C102/12,'Model inputs'!C104*MIN('Model inputs'!C110,'Model inputs'!C114))) -> 6000 | S94: =IF(EXACT("Cyber-cafes","Cyber-cafes"),'Model inputs'!C100*'Model inputs'!C108,IF(EXACT("Cyber-cafes","API"),'Model inputs'!C102/12,'Model inputs'!C104*MIN('Model inputs'!C110,'Model inputs'!C114))) -> 6000 | T94: =IF(EXACT("Cyber-cafes","Cyber-cafes"),'Model inputs'!C100*'Model inputs'!C108,IF(EXACT("Cyber-cafes","API"),'Model inputs'!C102/12,'Model inputs'!C104*MIN('Model inputs'!C110,'Model inputs'!C114))) -> 6000 | U94: =IF(EXACT("Cyber-cafes","Cyber-cafes"),'Model inputs'!C100*'Model inputs'!C108,IF(EXACT("Cyber-cafes","API"),'Model inputs'!C102/12,'Model inputs'!C104*MIN('Model inputs'!C110,'Model inputs'!C114))) -> 6000 | V94: =IF(EXACT("Cyber-cafes","Cyber-cafes"),'Model inputs'!C100*'Model inputs'!C108,IF(EXACT("Cyber-cafes","API"),'Model inputs'!C102/12,'Model inputs'!C104*MIN('Model inputs'!C110,'Model inputs'!C114))) -> 6000 | W94: =IF(EXACT("Cyber-cafes","Cyber-cafes"),'Model inputs'!C100*'Model inputs'!C108,IF(EXACT("Cyber-cafes","API"),'Model inputs'!C102/12,'Model inputs'!C104*MIN('Model inputs'!C110,'Model inputs'!C114))) -> 6000 | X94: =IF(EXACT("Cyber-cafes","Cyber-cafes"),'Model inputs'!C100*'Model inputs'!C108,IF(EXACT("Cyber-cafes","API"),'Model inputs'!C102/12,'Model inputs'!C104*MIN('Model inputs'!C110,'Model inputs'!C114))) -> 6000 | Y94: =IF(EXACT("Cyber-cafes","Cyber-cafes"),'Model inputs'!C100*'Model inputs'!C108,IF(EXACT("Cyber-cafes","API"),'Model inputs'!C102/12,'Model inputs'!C104*MIN('Model inputs'!C110,'Model inputs'!C114))) -> 6000 | Z94: =IF(EXACT("Cyber-cafes","Cyber-cafes"),'Model inputs'!C100*'Model inputs'!C108,IF(EXACT("Cyber-cafes","API"),'Model inputs'!C102/12,'Model inputs'!C104*MIN('Model inputs'!C110,'Model inputs'!C114))) -> 6000 | AA94: =IF(EXACT("Cyber-cafes","Cyber-cafes"),'Model inputs'!C100*'Model inputs'!C108,IF(EXACT("Cyber-cafes","API"),'Model inputs'!C102/12,'Model inputs'!C104*MIN('Model inputs'!C110,'Model inputs'!C114))) -> 6000
A95: NS checks > Students | D95: ='Model inputs'!D67 -> 0 | E95: ='Model inputs'!E67 -> 0 | F95: ='Model inputs'!F67 -> 0 | G95: ='Model inputs'!G67 -> 0 | H95: ='Model inputs'!H67 -> 0 | I95: ='Model inputs'!I67 -> 0 | J95: ='Model inputs'!J67 -> 0 | K95: ='Model inputs'!K67 -> 0 | L95: ='Model inputs'!L67 -> 0 | M95: =IF(EXACT("Students","Cyber-cafes"),'Model inputs'!C100*'Model inputs'!C108,IF(EXACT("Students","API"),'Model inputs'!C102/12,'Model inputs'!C104*MIN('Model inputs'!C110,'Model inputs'!C114))) -> 6000 | N95: =IF(EXACT("Students","Cyber-cafes"),'Model inputs'!C100*'Model inputs'!C108,IF(EXACT("Students","API"),'Model inputs'!C102/12,'Model inputs'!C104*MIN('Model inputs'!C110,'Model inputs'!C114))) -> 6000 | O95: =IF(EXACT("Students","Cyber-cafes"),'Model inputs'!C100*'Model inputs'!C108,IF(EXACT("Students","API"),'Model inputs'!C102/12,'Model inputs'!C104*MIN('Model inputs'!C110,'Model inputs'!C114))) -> 6000 | P95: =IF(EXACT("Students","Cyber-cafes"),'Model inputs'!C100*'Model inputs'!C108,IF(EXACT("Students","API"),'Model inputs'!C102/12,'Model inputs'!C104*MIN('Model inputs'!C110,'Model inputs'!C114))) -> 6000 | Q95: =IF(EXACT("Students","Cyber-cafes"),'Model inputs'!C100*'Model inputs'!C108,IF(EXACT("Students","API"),'Model inputs'!C102/12,'Model inputs'!C104*MIN('Model inputs'!C110,'Model inputs'!C114))) -> 6000 | R95: =IF(EXACT("Students","Cyber-cafes"),'Model inputs'!C100*'Model inputs'!C108,IF(EXACT("Students","API"),'Model inputs'!C102/12,'Model inputs'!C104*MIN('Model inputs'!C110,'Model inputs'!C114))) -> 6000 | S95: =IF(EXACT("Students","Cyber-cafes"),'Model inputs'!C100*'Model inputs'!C108,IF(EXACT("Students","API"),'Model inputs'!C102/12,'Model inputs'!C104*MIN('Model inputs'!C110,'Model inputs'!C114))) -> 6000 | T95: =IF(EXACT("Students","Cyber-cafes"),'Model inputs'!C100*'Model inputs'!C108,IF(EXACT("Students","API"),'Model inputs'!C102/12,'Model inputs'!C104*MIN('Model inputs'!C110,'Model inputs'!C114))) -> 6000 | U95: =IF(EXACT("Students","Cyber-cafes"),'Model inputs'!C100*'Model inputs'!C108,IF(EXACT("Students","API"),'Model inputs'!C102/12,'Model inputs'!C104*MIN('Model inputs'!C110,'Model inputs'!C114))) -> 6000 | V95: =IF(EXACT("Students","Cyber-cafes"),'Model inputs'!C100*'Model inputs'!C108,IF(EXACT("Students","API"),'Model inputs'!C102/12,'Model inputs'!C104*MIN('Model inputs'!C110,'Model inputs'!C114))) -> 6000 | W95: =IF(EXACT("Students","Cyber-cafes"),'Model inputs'!C100*'Model inputs'!C108,IF(EXACT("Students","API"),'Model inputs'!C102/12,'Model inputs'!C104*MIN('Model inputs'!C110,'Model inputs'!C114))) -> 6000 | X95: =IF(EXACT("Students","Cyber-cafes"),'Model inputs'!C100*'Model inputs'!C108,IF(EXACT("Students","API"),'Model inputs'!C102/12,'Model inputs'!C104*MIN('Model inputs'!C110,'Model inputs'!C114))) -> 6000 | Y95: =IF(EXACT("Students","Cyber-cafes"),'Model inputs'!C100*'Model inputs'!C108,IF(EXACT("Students","API"),'Model inputs'!C102/12,'Model inputs'!C104*MIN('Model inputs'!C110,'Model inputs'!C114))) -> 6000 | Z95: =IF(EXACT("Students","Cyber-cafes"),'Model inputs'!C100*'Model inputs'!C108,IF(EXACT("Students","API"),'Model inputs'!C102/12,'Model inputs'!C104*MIN('Model inputs'!C110,'Model inputs'!C114))) -> 6000 | AA95: =IF(EXACT("Students","Cyber-cafes"),'Model inputs'!C100*'Model inputs'!C108,IF(EXACT("Students","API"),'Model inputs'!C102/12,'Model inputs'!C104*MIN('Model inputs'!C110,'Model inputs'!C114))) -> 6000
A96: NS checks | D96: =SUM('Model inputs'!D97,'Model inputs'!D98,'Model inputs'!D99) -> 0 | E96: =SUM('Model inputs'!E97,'Model inputs'!E98,'Model inputs'!E99) -> 0 | F96: =SUM('Model inputs'!F97,'Model inputs'!F98,'Model inputs'!F99) -> 0 | G96: =SUM('Model inputs'!G97,'Model inputs'!G98,'Model inputs'!G99) -> 0 | H96: =SUM('Model inputs'!H97,'Model inputs'!H98,'Model inputs'!H99) -> 0 | I96: =SUM('Model inputs'!I97,'Model inputs'!I98,'Model inputs'!I99) -> 0 | J96: =SUM('Model inputs'!J97,'Model inputs'!J98,'Model inputs'!J99) -> 0 | K96: =SUM('Model inputs'!K97,'Model inputs'!K98,'Model inputs'!K99) -> 0 | ... AA96: =SUM('Model inputs'!AA97,'Model inputs'!AA98,'Model inputs'!AA99) -> 3200
A97: NS checks > API | D97: ='Model inputs'!D65 -> 0 | E97: ='Model inputs'!E65 -> 0 | F97: ='Model inputs'!F65 -> 0 | G97: ='Model inputs'!G65 -> 0 | H97: ='Model inputs'!H65 -> 0 | I97: ='Model inputs'!I65 -> 0 | J97: ='Model inputs'!J65 -> 0 | K97: ='Model inputs'!K65 -> 0 | L97: ='Model inputs'!L65 -> 0 | M97: =IF(EXACT("API","Cyber-cafes"),'Model inputs'!C101*'Model inputs'!C109,IF(EXACT("API","API"),'Model inputs'!C103/12,'Model inputs'!C105*MIN('Model inputs'!C111,'Model inputs'!C115))) -> 0 | N97: =IF(EXACT("API","Cyber-cafes"),'Model inputs'!C101*'Model inputs'!C109,IF(EXACT("API","API"),'Model inputs'!C103/12,'Model inputs'!C105*MIN('Model inputs'!C111,'Model inputs'!C115))) -> 0 | O97: =IF(EXACT("API","Cyber-cafes"),'Model inputs'!C101*'Model inputs'!C109,IF(EXACT("API","API"),'Model inputs'!C103/12,'Model inputs'!C105*MIN('Model inputs'!C111,'Model inputs'!C115))) -> 0 | P97: =IF(EXACT("API","Cyber-cafes"),'Model inputs'!C101*'Model inputs'!C109,IF(EXACT("API","API"),'Model inputs'!C103/12,'Model inputs'!C105*MIN('Model inputs'!C111,'Model inputs'!C115))) -> 0 | Q97: =IF(EXACT("API","Cyber-cafes"),'Model inputs'!C101*'Model inputs'!C109,IF(EXACT("API","API"),'Model inputs'!C103/12,'Model inputs'!C105*MIN('Model inputs'!C111,'Model inputs'!C115))) -> 0 | R97: =IF(EXACT("API","Cyber-cafes"),'Model inputs'!C101*'Model inputs'!C109,IF(EXACT("API","API"),'Model inputs'!C103/12,'Model inputs'!C105*MIN('Model inputs'!C111,'Model inputs'!C115))) -> 0 | S97: =IF(EXACT("API","Cyber-cafes"),'Model inputs'!C101*'Model inputs'!C109,IF(EXACT("API","API"),'Model inputs'!C103/12,'Model inputs'!C105*MIN('Model inputs'!C111,'Model inputs'!C115))) -> 0 | T97: =IF(EXACT("API","Cyber-cafes"),'Model inputs'!C101*'Model inputs'!C109,IF(EXACT("API","API"),'Model inputs'!C103/12,'Model inputs'!C105*MIN('Model inputs'!C111,'Model inputs'!C115))) -> 0 | U97: =IF(EXACT("API","Cyber-cafes"),'Model inputs'!C101*'Model inputs'!C109,IF(EXACT("API","API"),'Model inputs'!C103/12,'Model inputs'!C105*MIN('Model inputs'!C111,'Model inputs'!C115))) -> 0 | V97: =IF(EXACT("API","Cyber-cafes"),'Model inputs'!C101*'Model inputs'!C109,IF(EXACT("API","API"),'Model inputs'!C103/12,'Model inputs'!C105*MIN('Model inputs'!C111,'Model inputs'!C115))) -> 0 | W97: =IF(EXACT("API","Cyber-cafes"),'Model inputs'!C101*'Model inputs'!C109,IF(EXACT("API","API"),'Model inputs'!C103/12,'Model inputs'!C105*MIN('Model inputs'!C111,'Model inputs'!C115))) -> 0 | X97: =IF(EXACT("API","Cyber-cafes"),'Model inputs'!C101*'Model inputs'!C109,IF(EXACT("API","API"),'Model inputs'!C103/12,'Model inputs'!C105*MIN('Model inputs'!C111,'Model inputs'!C115))) -> 0 | Y97: =IF(EXACT("API","Cyber-cafes"),'Model inputs'!C101*'Model inputs'!C109,IF(EXACT("API","API"),'Model inputs'!C103/12,'Model inputs'!C105*MIN('Model inputs'!C111,'Model inputs'!C115))) -> 0 | Z97: =IF(EXACT("API","Cyber-cafes"),'Model inputs'!C101*'Model inputs'!C109,IF(EXACT("API","API"),'Model inputs'!C103/12,'Model inputs'!C105*MIN('Model inputs'!C111,'Model inputs'!C115))) -> 0 | AA97: =IF(EXACT("API","Cyber-cafes"),'Model inputs'!C101*'Model inputs'!C109,IF(EXACT("API","API"),'Model inputs'!C103/12,'Model inputs'!C105*MIN('Model inputs'!C111,'Model inputs'!C115))) -> 0
A98: NS checks > Cyber-cafes | D98: ='Model inputs'!D66 -> 0 | E98: ='Model inputs'!E66 -> 0 | F98: ='Model inputs'!F66 -> 0 | G98: ='Model inputs'!G66 -> 0 | H98: ='Model inputs'!H66 -> 0 | I98: ='Model inputs'!I66 -> 0 | J98: ='Model inputs'!J66 -> 0 | K98: ='Model inputs'!K66 -> 0 | L98: ='Model inputs'!L66 -> 0 | M98: =IF(EXACT("Cyber-cafes","Cyber-cafes"),'Model inputs'!C101*'Model inputs'!C109,IF(EXACT("Cyber-cafes","API"),'Model inputs'!C103/12,'Model inputs'!C105*MIN('Model inputs'!C111,'Model inputs'!C115))) -> 200 | N98: =IF(EXACT("Cyber-cafes","Cyber-cafes"),'Model inputs'!C101*'Model inputs'!C109,IF(EXACT("Cyber-cafes","API"),'Model inputs'!C103/12,'Model inputs'!C105*MIN('Model inputs'!C111,'Model inputs'!C115))) -> 200 | O98: =IF(EXACT("Cyber-cafes","Cyber-cafes"),'Model inputs'!C101*'Model inputs'!C109,IF(EXACT("Cyber-cafes","API"),'Model inputs'!C103/12,'Model inputs'!C105*MIN('Model inputs'!C111,'Model inputs'!C115))) -> 200 | P98: =IF(EXACT("Cyber-cafes","Cyber-cafes"),'Model inputs'!C101*'Model inputs'!C109,IF(EXACT("Cyber-cafes","API"),'Model inputs'!C103/12,'Model inputs'!C105*MIN('Model inputs'!C111,'Model inputs'!C115))) -> 200 | Q98: =IF(EXACT("Cyber-cafes","Cyber-cafes"),'Model inputs'!C101*'Model inputs'!C109,IF(EXACT("Cyber-cafes","API"),'Model inputs'!C103/12,'Model inputs'!C105*MIN('Model inputs'!C111,'Model inputs'!C115))) -> 200 | R98: =IF(EXACT("Cyber-cafes","Cyber-cafes"),'Model inputs'!C101*'Model inputs'!C109,IF(EXACT("Cyber-cafes","API"),'Model inputs'!C103/12,'Model inputs'!C105*MIN('Model inputs'!C111,'Model inputs'!C115))) -> 200 | S98: =IF(EXACT("Cyber-cafes","Cyber-cafes"),'Model inputs'!C101*'Model inputs'!C109,IF(EXACT("Cyber-cafes","API"),'Model inputs'!C103/12,'Model inputs'!C105*MIN('Model inputs'!C111,'Model inputs'!C115))) -> 200 | T98: =IF(EXACT("Cyber-cafes","Cyber-cafes"),'Model inputs'!C101*'Model inputs'!C109,IF(EXACT("Cyber-cafes","API"),'Model inputs'!C103/12,'Model inputs'!C105*MIN('Model inputs'!C111,'Model inputs'!C115))) -> 200 | U98: =IF(EXACT("Cyber-cafes","Cyber-cafes"),'Model inputs'!C101*'Model inputs'!C109,IF(EXACT("Cyber-cafes","API"),'Model inputs'!C103/12,'Model inputs'!C105*MIN('Model inputs'!C111,'Model inputs'!C115))) -> 200 | V98: =IF(EXACT("Cyber-cafes","Cyber-cafes"),'Model inputs'!C101*'Model inputs'!C109,IF(EXACT("Cyber-cafes","API"),'Model inputs'!C103/12,'Model inputs'!C105*MIN('Model inputs'!C111,'Model inputs'!C115))) -> 200 | W98: =IF(EXACT("Cyber-cafes","Cyber-cafes"),'Model inputs'!C101*'Model inputs'!C109,IF(EXACT("Cyber-cafes","API"),'Model inputs'!C103/12,'Model inputs'!C105*MIN('Model inputs'!C111,'Model inputs'!C115))) -> 200 | X98: =IF(EXACT("Cyber-cafes","Cyber-cafes"),'Model inputs'!C101*'Model inputs'!C109,IF(EXACT("Cyber-cafes","API"),'Model inputs'!C103/12,'Model inputs'!C105*MIN('Model inputs'!C111,'Model inputs'!C115))) -> 200 | Y98: =IF(EXACT("Cyber-cafes","Cyber-cafes"),'Model inputs'!C101*'Model inputs'!C109,IF(EXACT("Cyber-cafes","API"),'Model inputs'!C103/12,'Model inputs'!C105*MIN('Model inputs'!C111,'Model inputs'!C115))) -> 200 | Z98: =IF(EXACT("Cyber-cafes","Cyber-cafes"),'Model inputs'!C101*'Model inputs'!C109,IF(EXACT("Cyber-cafes","API"),'Model inputs'!C103/12,'Model inputs'!C105*MIN('Model inputs'!C111,'Model inputs'!C115))) -> 200 | AA98: =IF(EXACT("Cyber-cafes","Cyber-cafes"),'Model inputs'!C101*'Model inputs'!C109,IF(EXACT("Cyber-cafes","API"),'Model inputs'!C103/12,'Model inputs'!C105*MIN('Model inputs'!C111,'Model inputs'!C115))) -> 200
A99: NS checks > Students | D99: ='Model inputs'!D67 -> 0 | E99: ='Model inputs'!E67 -> 0 | F99: ='Model inputs'!F67 -> 0 | G99: ='Model inputs'!G67 -> 0 | H99: ='Model inputs'!H67 -> 0 | I99: ='Model inputs'!I67 -> 0 | J99: ='Model inputs'!J67 -> 0 | K99: ='Model inputs'!K67 -> 0 | L99: ='Model inputs'!L67 -> 0 | M99: =IF(EXACT("Students","Cyber-cafes"),'Model inputs'!C101*'Model inputs'!C109,IF(EXACT("Students","API"),'Model inputs'!C103/12,'Model inputs'!C105*MIN('Model inputs'!C111,'Model inputs'!C115))) -> 3000 | N99: =IF(EXACT("Students","Cyber-cafes"),'Model inputs'!C101*'Model inputs'!C109,IF(EXACT("Students","API"),'Model inputs'!C103/12,'Model inputs'!C105*MIN('Model inputs'!C111,'Model inputs'!C115))) -> 3000 | O99: =IF(EXACT("Students","Cyber-cafes"),'Model inputs'!C101*'Model inputs'!C109,IF(EXACT("Students","API"),'Model inputs'!C103/12,'Model inputs'!C105*MIN('Model inputs'!C111,'Model inputs'!C115))) -> 3000 | P99: =IF(EXACT("Students","Cyber-cafes"),'Model inputs'!C101*'Model inputs'!C109,IF(EXACT("Students","API"),'Model inputs'!C103/12,'Model inputs'!C105*MIN('Model inputs'!C111,'Model inputs'!C115))) -> 3000 | Q99: =IF(EXACT("Students","Cyber-cafes"),'Model inputs'!C101*'Model inputs'!C109,IF(EXACT("Students","API"),'Model inputs'!C103/12,'Model inputs'!C105*MIN('Model inputs'!C111,'Model inputs'!C115))) -> 3000 | R99: =IF(EXACT("Students","Cyber-cafes"),'Model inputs'!C101*'Model inputs'!C109,IF(EXACT("Students","API"),'Model inputs'!C103/12,'Model inputs'!C105*MIN('Model inputs'!C111,'Model inputs'!C115))) -> 3000 | S99: =IF(EXACT("Students","Cyber-cafes"),'Model inputs'!C101*'Model inputs'!C109,IF(EXACT("Students","API"),'Model inputs'!C103/12,'Model inputs'!C105*MIN('Model inputs'!C111,'Model inputs'!C115))) -> 3000 | T99: =IF(EXACT("Students","Cyber-cafes"),'Model inputs'!C101*'Model inputs'!C109,IF(EXACT("Students","API"),'Model inputs'!C103/12,'Model inputs'!C105*MIN('Model inputs'!C111,'Model inputs'!C115))) -> 3000 | U99: =IF(EXACT("Students","Cyber-cafes"),'Model inputs'!C101*'Model inputs'!C109,IF(EXACT("Students","API"),'Model inputs'!C103/12,'Model inputs'!C105*MIN('Model inputs'!C111,'Model inputs'!C115))) -> 3000 | V99: =IF(EXACT("Students","Cyber-cafes"),'Model inputs'!C101*'Model inputs'!C109,IF(EXACT("Students","API"),'Model inputs'!C103/12,'Model inputs'!C105*MIN('Model inputs'!C111,'Model inputs'!C115))) -> 3000 | W99: =IF(EXACT("Students","Cyber-cafes"),'Model inputs'!C101*'Model inputs'!C109,IF(EXACT("Students","API"),'Model inputs'!C103/12,'Model inputs'!C105*MIN('Model inputs'!C111,'Model inputs'!C115))) -> 3000 | X99: =IF(EXACT("Students","Cyber-cafes"),'Model inputs'!C101*'Model inputs'!C109,IF(EXACT("Students","API"),'Model inputs'!C103/12,'Model inputs'!C105*MIN('Model inputs'!C111,'Model inputs'!C115))) -> 3000 | Y99: =IF(EXACT("Students","Cyber-cafes"),'Model inputs'!C101*'Model inputs'!C109,IF(EXACT("Students","API"),'Model inputs'!C103/12,'Model inputs'!C105*MIN('Model inputs'!C111,'Model inputs'!C115))) -> 3000 | Z99: =IF(EXACT("Students","Cyber-cafes"),'Model inputs'!C101*'Model inputs'!C109,IF(EXACT("Students","API"),'Model inputs'!C103/12,'Model inputs'!C105*MIN('Model inputs'!C111,'Model inputs'!C115))) -> 3000 | AA99: =IF(EXACT("Students","Cyber-cafes"),'Model inputs'!C101*'Model inputs'!C109,IF(EXACT("Students","API"),'Model inputs'!C103/12,'Model inputs'!C105*MIN('Model inputs'!C111,'Model inputs'!C115))) -> 3000
A100: Paying cafes · NS revenue · by NS customer channel · NaukriShield — Upside · NaukriShield — Upside | C100: =300 -> 300
A101: Paying cafes · NS revenue · by NS customer channel · NaukriShield — Downside · NaukriShield — Downside | C101: =20 -> 20
...
